<?xml version="1.0" ?>
<wml2:Collection xmlns:xsi="http://www.w3.org/2001/XMLSchema-instance" xmlns:xlink="http://www.w3.org/1999/xlink" xmlns:gml="http://www.opengis.net/gml/3.2" xmlns:ogc="http://www.opengis.net/ogc" xmlns:om="http://www.opengis.net/om/2.0" xmlns:wml2="http://www.opengis.net/waterml/2.0" xsi:schemaLocation="http://www.opengis.net/waterml/2.0 http://schemas.opengis.net/waterml/2.0/waterml2.xsd" gml:id="wml2.collection.1">
<wml2:metadata xlink:href="http://www.opengis.net/def/nil/OGC/0/missing" />
<wml2:localDictionary>
<gml:Dictionary gml:id="TransferRules">
<gml:dictionaryEntry>
<gml:Definition gml:id="ServiceProvider">
<gml:identifier>ServiceProvider</gml:identifier>
<gml:name>Horizons</gml:name>
</gml:Definition>
</gml:dictionaryEntry>
</gml:Dictionary>
</wml2:localDictionary>
<wml2:observationMember><om:OM_Observation gml:id="om.1">
<om:procedure xlink:title="Water Level (Daily Mean)" />
<om:observedProperty xlink:title="Stage MSL" />
<om:featureOfInterest xlink:title="Mangatainoka at Larsons Road" />
<om:result><wml2:MeasurementTimeseries gml:id="mt.1">
<wml2:defaultPointMetadata>
<wml2:DefaultTVPMeasurementMetadata>
<wml2:interpolationType xlink:title="Continuous" xlink:href="http://www.opengis.net/def/waterml/2.0/interpolationType/Continuous" />
<wml2:uom code="mm" />
</wml2:DefaultTVPMeasurementMetadata>
</wml2:defaultPointMetadata>
<wml2:point><wml2:MeasurementTVP><wml2:time>2015-10-01T00:00:00+12:00</wml2:time><wml2:value>256654</wml2:value></wml2:MeasurementTVP></wml2:point>
<wml2:point><wml2:MeasurementTVP><wml2:time>2015-10-02T00:00:00+12:00</wml2:time><wml2:value>256680</wml2:value></wml2:MeasurementTVP></wml2:point>
<wml2:point><wml2:MeasurementTVP><wml2:time>2015-10-03T00:00:00+12:00</wml2:time><wml2:value>256906</wml2:value></wml2:MeasurementTVP></wml2:point>
<wml2:point><wml2:MeasurementTVP><wml2:time>2015-10-04T00:00:00+12:00</wml2:time><wml2:value>256735</wml2:value></wml2:MeasurementTVP></wml2:point>
<wml2:point><wml2:MeasurementTVP><wml2:time>2015-10-05T00:00:00+12:00</wml2:time><wml2:value>256706</wml2:value></wml2:MeasurementTVP></wml2:point>
<wml2:point><wml2:MeasurementTVP><wml2:time>2015-10-06T00:00:00+12:00</wml2:time><wml2:value>256698</wml2:value></wml2:MeasurementTVP></wml2:point>
<wml2:point><wml2:MeasurementTVP><wml2:time>2015-10-07T00:00:00+12:00</wml2:time><wml2:value>256650</wml2:value></wml2:MeasurementTVP></wml2:point>
<wml2:point><wml2:MeasurementTVP><wml2:time>2015-10-08T00:00:00+12:00</wml2:time><wml2:value>256628</wml2:value></wml2:MeasurementTVP></wml2:point>
<wml2:point><wml2:MeasurementTVP><wml2:time>2015-10-09T00:00:00+12:00</wml2:time><wml2:value>256811</wml2:value></wml2:MeasurementTVP></wml2:point>
<wml2:point><wml2:MeasurementTVP><wml2:time>2015-10-10T00:00:00+12:00</wml2:time><wml2:value>256687</wml2:value></wml2:MeasurementTVP></wml2:point>
<wml2:point><wml2:MeasurementTVP><wml2:time>2015-10-11T00:00:00+12:00</wml2:time><wml2:value>256648</wml2:value></wml2:MeasurementTVP></wml2:point>
<wml2:point><wml2:MeasurementTVP><wml2:time>2015-10-12T00:00:00+12:00</wml2:time><wml2:value>256626</wml2:value></wml2:MeasurementTVP></wml2:point>
<wml2:point><wml2:MeasurementTVP><wml2:time>2015-10-13T00:00:00+12:00</wml2:time><wml2:value>256636</wml2:value></wml2:MeasurementTVP></wml2:point>
<wml2:point><wml2:MeasurementTVP><wml2:time>2015-10-14T00:00:00+12:00</wml2:time><wml2:value>256964</wml2:value></wml2:MeasurementTVP></wml2:point>
<wml2:point><wml2:MeasurementTVP><wml2:time>2015-10-15T00:00:00+12:00</wml2:time><wml2:value>256848</wml2:value></wml2:MeasurementTVP></wml2:point>
<wml2:point><wml2:MeasurementTVP><wml2:time>2015-10-16T00:00:00+12:00</wml2:time><wml2:value>256721</wml2:value></wml2:MeasurementTVP></wml2:point>
<wml2:point><wml2:MeasurementTVP><wml2:time>2015-10-17T00:00:00+12:00</wml2:time><wml2:value>256678</wml2:value></wml2:MeasurementTVP></wml2:point>
<wml2:point><wml2:MeasurementTVP><wml2:time>2015-10-18T00:00:00+12:00</wml2:time><wml2:value>256761</wml2:value></wml2:MeasurementTVP></wml2:point>
<wml2:point><wml2:MeasurementTVP><wml2:time>2015-10-19T00:00:00+12:00</wml2:time><wml2:value>257942</wml2:value></wml2:MeasurementTVP></wml2:point>
<wml2:point><wml2:MeasurementTVP><wml2:time>2015-10-20T00:00:00+12:00</wml2:time><wml2:value>257070</wml2:value></wml2:MeasurementTVP></wml2:point>
<wml2:point><wml2:MeasurementTVP><wml2:time>2015-10-21T00:00:00+12:00</wml2:time><wml2:value>256842</wml2:value></wml2:MeasurementTVP></wml2:point>
<wml2:point><wml2:MeasurementTVP><wml2:time>2015-10-22T00:00:00+12:00</wml2:time><wml2:value>256759</wml2:value></wml2:MeasurementTVP></wml2:point>
<wml2:point><wml2:MeasurementTVP><wml2:time>2015-10-23T00:00:00+12:00</wml2:time><wml2:value>257184</wml2:value></wml2:MeasurementTVP></wml2:point>
<wml2:point><wml2:MeasurementTVP><wml2:time>2015-10-24T00:00:00+12:00</wml2:time><wml2:value>257401</wml2:value></wml2:MeasurementTVP></wml2:point>
<wml2:point><wml2:MeasurementTVP><wml2:time>2015-10-25T00:00:00+12:00</wml2:time><wml2:value>257282</wml2:value></wml2:MeasurementTVP></wml2:point>
<wml2:point><wml2:MeasurementTVP><wml2:time>2015-10-26T00:00:00+12:00</wml2:time><wml2:value>256894</wml2:value></wml2:MeasurementTVP></wml2:point>
<wml2:point><wml2:MeasurementTVP><wml2:time>2015-10-27T00:00:00+12:00</wml2:time><wml2:value>256784</wml2:value></wml2:MeasurementTVP></wml2:point>
<wml2:point><wml2:MeasurementTVP><wml2:time>2015-10-28T00:00:00+12:00</wml2:time><wml2:value>256726</wml2:value></wml2:MeasurementTVP></wml2:point>
<wml2:point><wml2:MeasurementTVP><wml2:time>2015-10-29T00:00:00+12:00</wml2:time><wml2:value>256695</wml2:value></wml2:MeasurementTVP></wml2:point>
<wml2:point><wml2:MeasurementTVP><wml2:time>2015-10-30T00:00:00+12:00</wml2:time><wml2:value>257264</wml2:value></wml2:MeasurementTVP></wml2:point>
<wml2:point><wml2:MeasurementTVP><wml2:time>2015-10-31T00:00:00+12:00</wml2:time><wml2:value>256944</wml2:value></wml2:MeasurementTVP></wml2:point>
<wml2:point><wml2:MeasurementTVP><wml2:time>2015-11-01T00:00:00+12:00</wml2:time><wml2:value>256790</wml2:value></wml2:MeasurementTVP></wml2:point>
<wml2:point><wml2:MeasurementTVP><wml2:time>2015-11-02T00:00:00+12:00</wml2:time><wml2:value>256725</wml2:value></wml2:MeasurementTVP></wml2:point>
<wml2:point><wml2:MeasurementTVP><wml2:time>2015-11-03T00:00:00+12:00</wml2:time><wml2:value>256683</wml2:value></wml2:MeasurementTVP></wml2:point>
<wml2:point><wml2:MeasurementTVP><wml2:time>2015-11-04T00:00:00+12:00</wml2:time><wml2:value>256772</wml2:value></wml2:MeasurementTVP></wml2:point>
<wml2:point><wml2:MeasurementTVP><wml2:time>2015-11-05T00:00:00+12:00</wml2:time><wml2:value>257404</wml2:value></wml2:MeasurementTVP></wml2:point>
<wml2:point><wml2:MeasurementTVP><wml2:time>2015-11-06T00:00:00+12:00</wml2:time><wml2:value>256914</wml2:value></wml2:MeasurementTVP></wml2:point>
<wml2:point><wml2:MeasurementTVP><wml2:time>2015-11-07T00:00:00+12:00</wml2:time><wml2:value>256787</wml2:value></wml2:MeasurementTVP></wml2:point>
<wml2:point><wml2:MeasurementTVP><wml2:time>2015-11-08T00:00:00+12:00</wml2:time><wml2:value>256720</wml2:value></wml2:MeasurementTVP></wml2:point>
<wml2:point><wml2:MeasurementTVP><wml2:time>2015-11-09T00:00:00+12:00</wml2:time><wml2:value>256674</wml2:value></wml2:MeasurementTVP></wml2:point>
<wml2:point><wml2:MeasurementTVP><wml2:time>2015-11-10T00:00:00+12:00</wml2:time><wml2:value>256646</wml2:value></wml2:MeasurementTVP></wml2:point>
<wml2:point><wml2:MeasurementTVP><wml2:time>2015-11-11T00:00:00+12:00</wml2:time><wml2:value>256626</wml2:value></wml2:MeasurementTVP></wml2:point>
<wml2:point><wml2:MeasurementTVP><wml2:time>2015-11-12T00:00:00+12:00</wml2:time><wml2:value>256619</wml2:value></wml2:MeasurementTVP></wml2:point>
<wml2:point><wml2:MeasurementTVP><wml2:time>2015-11-13T00:00:00+12:00</wml2:time><wml2:value>256629</wml2:value></wml2:MeasurementTVP></wml2:point>
<wml2:point><wml2:MeasurementTVP><wml2:time>2015-11-14T00:00:00+12:00</wml2:time><wml2:value>256598</wml2:value></wml2:MeasurementTVP></wml2:point>
<wml2:point><wml2:MeasurementTVP><wml2:time>2015-11-15T00:00:00+12:00</wml2:time><wml2:value>256580</wml2:value></wml2:MeasurementTVP></wml2:point>
<wml2:point><wml2:MeasurementTVP><wml2:time>2015-11-16T00:00:00+12:00</wml2:time><wml2:value>256928</wml2:value></wml2:MeasurementTVP></wml2:point>
<wml2:point><wml2:MeasurementTVP><wml2:time>2015-11-17T00:00:00+12:00</wml2:time><wml2:value>256740</wml2:value></wml2:MeasurementTVP></wml2:point>
<wml2:point><wml2:MeasurementTVP><wml2:time>2015-11-18T00:00:00+12:00</wml2:time><wml2:value>256666</wml2:value></wml2:MeasurementTVP></wml2:point>
<wml2:point><wml2:MeasurementTVP><wml2:time>2015-11-19T00:00:00+12:00</wml2:time><wml2:value>256660</wml2:value></wml2:MeasurementTVP></wml2:point>
<wml2:point><wml2:MeasurementTVP><wml2:time>2015-11-20T00:00:00+12:00</wml2:time><wml2:value>256636</wml2:value></wml2:MeasurementTVP></wml2:point>
<wml2:point><wml2:MeasurementTVP><wml2:time>2015-11-21T00:00:00+12:00</wml2:time><wml2:value>257049</wml2:value></wml2:MeasurementTVP></wml2:point>
<wml2:point><wml2:MeasurementTVP><wml2:time>2015-11-22T00:00:00+12:00</wml2:time><wml2:value>257245</wml2:value></wml2:MeasurementTVP></wml2:point>
<wml2:point><wml2:MeasurementTVP><wml2:time>2015-11-23T00:00:00+12:00</wml2:time><wml2:value>256936</wml2:value></wml2:MeasurementTVP></wml2:point>
<wml2:point><wml2:MeasurementTVP><wml2:time>2015-11-24T00:00:00+12:00</wml2:time><wml2:value>256777</wml2:value></wml2:MeasurementTVP></wml2:point>
<wml2:point><wml2:MeasurementTVP><wml2:time>2015-11-25T00:00:00+12:00</wml2:time><wml2:value>256708</wml2:value></wml2:MeasurementTVP></wml2:point>
<wml2:point><wml2:MeasurementTVP><wml2:time>2015-11-26T00:00:00+12:00</wml2:time><wml2:value>256669</wml2:value></wml2:MeasurementTVP></wml2:point>
<wml2:point><wml2:MeasurementTVP><wml2:time>2015-11-27T00:00:00+12:00</wml2:time><wml2:value>256685</wml2:value></wml2:MeasurementTVP></wml2:point>
<wml2:point><wml2:MeasurementTVP><wml2:time>2015-11-28T00:00:00+12:00</wml2:time><wml2:value>256663</wml2:value></wml2:MeasurementTVP></wml2:point>
<wml2:point><wml2:MeasurementTVP><wml2:time>2015-11-29T00:00:00+12:00</wml2:time><wml2:value>257069</wml2:value></wml2:MeasurementTVP></wml2:point>
<wml2:point><wml2:MeasurementTVP><wml2:time>2015-11-30T00:00:00+12:00</wml2:time><wml2:value>256759</wml2:value></wml2:MeasurementTVP></wml2:point>
<wml2:point><wml2:MeasurementTVP><wml2:time>2015-12-01T00:00:00+12:00</wml2:time><wml2:value>256691</wml2:value></wml2:MeasurementTVP></wml2:point>
<wml2:point><wml2:MeasurementTVP><wml2:time>2015-12-02T00:00:00+12:00</wml2:time><wml2:value>256728</wml2:value></wml2:MeasurementTVP></wml2:point>
<wml2:point><wml2:MeasurementTVP><wml2:time>2015-12-03T00:00:00+12:00</wml2:time><wml2:value>256721</wml2:value></wml2:MeasurementTVP></wml2:point>
<wml2:point><wml2:MeasurementTVP><wml2:time>2015-12-04T00:00:00+12:00</wml2:time><wml2:value>256665</wml2:value></wml2:MeasurementTVP></wml2:point>
<wml2:point><wml2:MeasurementTVP><wml2:time>2015-12-05T00:00:00+12:00</wml2:time><wml2:value>257129</wml2:value></wml2:MeasurementTVP></wml2:point>
<wml2:point><wml2:MeasurementTVP><wml2:time>2015-12-06T00:00:00+12:00</wml2:time><wml2:value>256796</wml2:value></wml2:MeasurementTVP></wml2:point>
<wml2:point><wml2:MeasurementTVP><wml2:time>2015-12-07T00:00:00+12:00</wml2:time><wml2:value>256982</wml2:value></wml2:MeasurementTVP></wml2:point>
<wml2:point><wml2:MeasurementTVP><wml2:time>2015-12-08T00:00:00+12:00</wml2:time><wml2:value>256879</wml2:value></wml2:MeasurementTVP></wml2:point>
<wml2:point><wml2:MeasurementTVP><wml2:time>2015-12-09T00:00:00+12:00</wml2:time><wml2:value>256754</wml2:value></wml2:MeasurementTVP></wml2:point>
<wml2:point><wml2:MeasurementTVP><wml2:time>2015-12-10T00:00:00+12:00</wml2:time><wml2:value>256693</wml2:value></wml2:MeasurementTVP></wml2:point>
<wml2:point><wml2:MeasurementTVP><wml2:time>2015-12-11T00:00:00+12:00</wml2:time><wml2:value>256659</wml2:value></wml2:MeasurementTVP></wml2:point>
<wml2:point><wml2:MeasurementTVP><wml2:time>2015-12-12T00:00:00+12:00</wml2:time><wml2:value>256724</wml2:value></wml2:MeasurementTVP></wml2:point>
<wml2:point><wml2:MeasurementTVP><wml2:time>2015-12-13T00:00:00+12:00</wml2:time><wml2:value>256671</wml2:value></wml2:MeasurementTVP></wml2:point>
<wml2:point><wml2:MeasurementTVP><wml2:time>2015-12-14T00:00:00+12:00</wml2:time><wml2:value>256731</wml2:value></wml2:MeasurementTVP></wml2:point>
<wml2:point><wml2:MeasurementTVP><wml2:time>2015-12-15T00:00:00+12:00</wml2:time><wml2:value>256633</wml2:value></wml2:MeasurementTVP></wml2:point>
<wml2:point><wml2:MeasurementTVP><wml2:time>2015-12-16T00:00:00+12:00</wml2:time><wml2:value>256605</wml2:value></wml2:MeasurementTVP></wml2:point>
<wml2:point><wml2:MeasurementTVP><wml2:time>2015-12-17T00:00:00+12:00</wml2:time><wml2:value>256740</wml2:value></wml2:MeasurementTVP></wml2:point>
<wml2:point><wml2:MeasurementTVP><wml2:time>2015-12-18T00:00:00+12:00</wml2:time><wml2:value>256771</wml2:value></wml2:MeasurementTVP></wml2:point>
<wml2:point><wml2:MeasurementTVP><wml2:time>2015-12-19T00:00:00+12:00</wml2:time><wml2:value>256674</wml2:value></wml2:MeasurementTVP></wml2:point>
<wml2:point><wml2:MeasurementTVP><wml2:time>2015-12-20T00:00:00+12:00</wml2:time><wml2:value>256632</wml2:value></wml2:MeasurementTVP></wml2:point>
<wml2:point><wml2:MeasurementTVP><wml2:time>2015-12-21T00:00:00+12:00</wml2:time><wml2:value>256605</wml2:value></wml2:MeasurementTVP></wml2:point>
<wml2:point><wml2:MeasurementTVP><wml2:time>2015-12-22T00:00:00+12:00</wml2:time><wml2:value>256588</wml2:value></wml2:MeasurementTVP></wml2:point>
<wml2:point><wml2:MeasurementTVP><wml2:time>2015-12-23T00:00:00+12:00</wml2:time><wml2:value>256724</wml2:value></wml2:MeasurementTVP></wml2:point>
<wml2:point><wml2:MeasurementTVP><wml2:time>2015-12-24T00:00:00+12:00</wml2:time><wml2:value>256699</wml2:value></wml2:MeasurementTVP></wml2:point>
<wml2:point><wml2:MeasurementTVP><wml2:time>2015-12-25T00:00:00+12:00</wml2:time><wml2:value>256617</wml2:value></wml2:MeasurementTVP></wml2:point>
<wml2:point><wml2:MeasurementTVP><wml2:time>2015-12-26T00:00:00+12:00</wml2:time><wml2:value>256591</wml2:value></wml2:MeasurementTVP></wml2:point>
<wml2:point><wml2:MeasurementTVP><wml2:time>2015-12-27T00:00:00+12:00</wml2:time><wml2:value>256574</wml2:value></wml2:MeasurementTVP></wml2:point>
<wml2:point><wml2:MeasurementTVP><wml2:time>2015-12-28T00:00:00+12:00</wml2:time><wml2:value>256560</wml2:value></wml2:MeasurementTVP></wml2:point>
<wml2:point><wml2:MeasurementTVP><wml2:time>2015-12-29T00:00:00+12:00</wml2:time><wml2:value>256549</wml2:value></wml2:MeasurementTVP></wml2:point>
<wml2:point><wml2:MeasurementTVP><wml2:time>2015-12-30T00:00:00+12:00</wml2:time><wml2:value>256538</wml2:value></wml2:MeasurementTVP></wml2:point>
<wml2:point><wml2:MeasurementTVP><wml2:time>2015-12-31T00:00:00+12:00</wml2:time><wml2:value>256530</wml2:value></wml2:MeasurementTVP></wml2:point>
<wml2:point><wml2:MeasurementTVP><wml2:time>2016-01-01T00:00:00+12:00</wml2:time><wml2:value>256562</wml2:value></wml2:MeasurementTVP></wml2:point>
<wml2:point><wml2:MeasurementTVP><wml2:time>2016-01-02T00:00:00+12:00</wml2:time><wml2:value>256534</wml2:value></wml2:MeasurementTVP></wml2:point>
<wml2:point><wml2:MeasurementTVP><wml2:time>2016-01-03T00:00:00+12:00</wml2:time><wml2:value>256556</wml2:value></wml2:MeasurementTVP></wml2:point>
<wml2:point><wml2:MeasurementTVP><wml2:time>2016-01-04T00:00:00+12:00</wml2:time><wml2:value>256696</wml2:value></wml2:MeasurementTVP></wml2:point>
<wml2:point><wml2:MeasurementTVP><wml2:time>2016-01-05T00:00:00+12:00</wml2:time><wml2:value>256758</wml2:value></wml2:MeasurementTVP></wml2:point>
<wml2:point><wml2:MeasurementTVP><wml2:time>2016-01-06T00:00:00+12:00</wml2:time><wml2:value>256608</wml2:value></wml2:MeasurementTVP></wml2:point>
<wml2:point><wml2:MeasurementTVP><wml2:time>2016-01-07T00:00:00+12:00</wml2:time><wml2:value>256570</wml2:value></wml2:MeasurementTVP></wml2:point>
<wml2:point><wml2:MeasurementTVP><wml2:time>2016-01-08T00:00:00+12:00</wml2:time><wml2:value>256551</wml2:value></wml2:MeasurementTVP></wml2:point>
<wml2:point><wml2:MeasurementTVP><wml2:time>2016-01-09T00:00:00+12:00</wml2:time><wml2:value>256949</wml2:value></wml2:MeasurementTVP></wml2:point>
<wml2:point><wml2:MeasurementTVP><wml2:time>2016-01-10T00:00:00+12:00</wml2:time><wml2:value>256890</wml2:value></wml2:MeasurementTVP></wml2:point>
<wml2:point><wml2:MeasurementTVP><wml2:time>2016-01-11T00:00:00+12:00</wml2:time><wml2:value>256721</wml2:value></wml2:MeasurementTVP></wml2:point>
<wml2:point><wml2:MeasurementTVP><wml2:time>2016-01-12T00:00:00+12:00</wml2:time><wml2:value>256656</wml2:value></wml2:MeasurementTVP></wml2:point>
<wml2:point><wml2:MeasurementTVP><wml2:time>2016-01-13T00:00:00+12:00</wml2:time><wml2:value>256620</wml2:value></wml2:MeasurementTVP></wml2:point>
<wml2:point><wml2:MeasurementTVP><wml2:time>2016-01-14T00:00:00+12:00</wml2:time><wml2:value>256595</wml2:value></wml2:MeasurementTVP></wml2:point>
<wml2:point><wml2:MeasurementTVP><wml2:time>2016-01-15T00:00:00+12:00</wml2:time><wml2:value>256582</wml2:value></wml2:MeasurementTVP></wml2:point>
<wml2:point><wml2:MeasurementTVP><wml2:time>2016-01-16T00:00:00+12:00</wml2:time><wml2:value>256563</wml2:value></wml2:MeasurementTVP></wml2:point>
<wml2:point><wml2:MeasurementTVP><wml2:time>2016-01-17T00:00:00+12:00</wml2:time><wml2:value>256563</wml2:value></wml2:MeasurementTVP></wml2:point>
<wml2:point><wml2:MeasurementTVP><wml2:time>2016-01-18T00:00:00+12:00</wml2:time><wml2:value>256574</wml2:value></wml2:MeasurementTVP></wml2:point>
<wml2:point><wml2:MeasurementTVP><wml2:time>2016-01-19T00:00:00+12:00</wml2:time><wml2:value>256595</wml2:value></wml2:MeasurementTVP></wml2:point>
<wml2:point><wml2:MeasurementTVP><wml2:time>2016-01-20T00:00:00+12:00</wml2:time><wml2:value>256906</wml2:value></wml2:MeasurementTVP></wml2:point>
<wml2:point><wml2:MeasurementTVP><wml2:time>2016-01-21T00:00:00+12:00</wml2:time><wml2:value>256722</wml2:value></wml2:MeasurementTVP></wml2:point>
<wml2:point><wml2:MeasurementTVP><wml2:time>2016-01-22T00:00:00+12:00</wml2:time><wml2:value>256641</wml2:value></wml2:MeasurementTVP></wml2:point>
<wml2:point><wml2:MeasurementTVP><wml2:time>2016-01-23T00:00:00+12:00</wml2:time><wml2:value>256603</wml2:value></wml2:MeasurementTVP></wml2:point>
<wml2:point><wml2:MeasurementTVP><wml2:time>2016-01-24T00:00:00+12:00</wml2:time><wml2:value>256589</wml2:value></wml2:MeasurementTVP></wml2:point>
<wml2:point><wml2:MeasurementTVP><wml2:time>2016-01-25T00:00:00+12:00</wml2:time><wml2:value>256564</wml2:value></wml2:MeasurementTVP></wml2:point>
<wml2:point><wml2:MeasurementTVP><wml2:time>2016-01-26T00:00:00+12:00</wml2:time><wml2:value>256545</wml2:value></wml2:MeasurementTVP></wml2:point>
<wml2:point><wml2:MeasurementTVP><wml2:time>2016-01-27T00:00:00+12:00</wml2:time><wml2:value>256535</wml2:value></wml2:MeasurementTVP></wml2:point>
<wml2:point><wml2:MeasurementTVP><wml2:time>2016-01-28T00:00:00+12:00</wml2:time><wml2:value>256578</wml2:value></wml2:MeasurementTVP></wml2:point>
<wml2:point><wml2:MeasurementTVP><wml2:time>2016-01-29T00:00:00+12:00</wml2:time><wml2:value>256568</wml2:value></wml2:MeasurementTVP></wml2:point>
<wml2:point><wml2:MeasurementTVP><wml2:time>2016-01-30T00:00:00+12:00</wml2:time><wml2:value>256537</wml2:value></wml2:MeasurementTVP></wml2:point>
<wml2:point><wml2:MeasurementTVP><wml2:time>2016-01-31T00:00:00+12:00</wml2:time><wml2:value>256526</wml2:value></wml2:MeasurementTVP></wml2:point>
<wml2:point><wml2:MeasurementTVP><wml2:time>2016-02-01T00:00:00+12:00</wml2:time><wml2:value>256521</wml2:value></wml2:MeasurementTVP></wml2:point>
<wml2:point><wml2:MeasurementTVP><wml2:time>2016-02-02T00:00:00+12:00</wml2:time><wml2:value>256515</wml2:value></wml2:MeasurementTVP></wml2:point>
<wml2:point><wml2:MeasurementTVP><wml2:time>2016-02-03T00:00:00+12:00</wml2:time><wml2:value>256506</wml2:value></wml2:MeasurementTVP></wml2:point>
<wml2:point><wml2:MeasurementTVP><wml2:time>2016-02-04T00:00:00+12:00</wml2:time><wml2:value>256500</wml2:value></wml2:MeasurementTVP></wml2:point>
<wml2:point><wml2:MeasurementTVP><wml2:time>2016-02-05T00:00:00+12:00</wml2:time><wml2:value>256494</wml2:value></wml2:MeasurementTVP></wml2:point>
<wml2:point><wml2:MeasurementTVP><wml2:time>2016-02-06T00:00:00+12:00</wml2:time><wml2:value>256489</wml2:value></wml2:MeasurementTVP></wml2:point>
<wml2:point><wml2:MeasurementTVP><wml2:time>2016-02-07T00:00:00+12:00</wml2:time><wml2:value>256486</wml2:value></wml2:MeasurementTVP></wml2:point>
<wml2:point><wml2:MeasurementTVP><wml2:time>2016-02-08T00:00:00+12:00</wml2:time><wml2:value>256483</wml2:value></wml2:MeasurementTVP></wml2:point>
<wml2:point><wml2:MeasurementTVP><wml2:time>2016-02-09T00:00:00+12:00</wml2:time><wml2:value>256483</wml2:value></wml2:MeasurementTVP></wml2:point>
<wml2:point><wml2:MeasurementTVP><wml2:time>2016-02-10T00:00:00+12:00</wml2:time><wml2:value>256480</wml2:value></wml2:MeasurementTVP></wml2:point>
<wml2:point><wml2:MeasurementTVP><wml2:time>2016-02-11T00:00:00+12:00</wml2:time><wml2:value>256477</wml2:value></wml2:MeasurementTVP></wml2:point>
<wml2:point><wml2:MeasurementTVP><wml2:time>2016-02-12T00:00:00+12:00</wml2:time><wml2:value>256474</wml2:value></wml2:MeasurementTVP></wml2:point>
<wml2:point><wml2:MeasurementTVP><wml2:time>2016-02-13T00:00:00+12:00</wml2:time><wml2:value>256469</wml2:value></wml2:MeasurementTVP></wml2:point>
<wml2:point><wml2:MeasurementTVP><wml2:time>2016-02-14T00:00:00+12:00</wml2:time><wml2:value>256466</wml2:value></wml2:MeasurementTVP></wml2:point>
<wml2:point><wml2:MeasurementTVP><wml2:time>2016-02-15T00:00:00+12:00</wml2:time><wml2:value>256464</wml2:value></wml2:MeasurementTVP></wml2:point>
<wml2:point><wml2:MeasurementTVP><wml2:time>2016-02-16T00:00:00+12:00</wml2:time><wml2:value>256462</wml2:value></wml2:MeasurementTVP></wml2:point>
<wml2:point><wml2:MeasurementTVP><wml2:time>2016-02-17T00:00:00+12:00</wml2:time><wml2:value>256460</wml2:value></wml2:MeasurementTVP></wml2:point>
<wml2:point><wml2:MeasurementTVP><wml2:time>2016-02-18T00:00:00+12:00</wml2:time><wml2:value>256465</wml2:value></wml2:MeasurementTVP></wml2:point>
<wml2:point><wml2:MeasurementTVP><wml2:time>2016-02-19T00:00:00+12:00</wml2:time><wml2:value>256576</wml2:value></wml2:MeasurementTVP></wml2:point>
<wml2:point><wml2:MeasurementTVP><wml2:time>2016-02-20T00:00:00+12:00</wml2:time><wml2:value>256697</wml2:value></wml2:MeasurementTVP></wml2:point>
<wml2:point><wml2:MeasurementTVP><wml2:time>2016-02-21T00:00:00+12:00</wml2:time><wml2:value>256574</wml2:value></wml2:MeasurementTVP></wml2:point>
<wml2:point><wml2:MeasurementTVP><wml2:time>2016-02-22T00:00:00+12:00</wml2:time><wml2:value>256514</wml2:value></wml2:MeasurementTVP></wml2:point>
<wml2:point><wml2:MeasurementTVP><wml2:time>2016-02-23T00:00:00+12:00</wml2:time><wml2:value>256496</wml2:value></wml2:MeasurementTVP></wml2:point>
<wml2:point><wml2:MeasurementTVP><wml2:time>2016-02-24T00:00:00+12:00</wml2:time><wml2:value>256485</wml2:value></wml2:MeasurementTVP></wml2:point>
<wml2:point><wml2:MeasurementTVP><wml2:time>2016-02-25T00:00:00+12:00</wml2:time><wml2:value>256478</wml2:value></wml2:MeasurementTVP></wml2:point>
<wml2:point><wml2:MeasurementTVP><wml2:time>2016-02-26T00:00:00+12:00</wml2:time><wml2:value>256498</wml2:value></wml2:MeasurementTVP></wml2:point>
<wml2:point><wml2:MeasurementTVP><wml2:time>2016-02-27T00:00:00+12:00</wml2:time><wml2:value>256513</wml2:value></wml2:MeasurementTVP></wml2:point>
<wml2:point><wml2:MeasurementTVP><wml2:time>2016-02-28T00:00:00+12:00</wml2:time><wml2:value>256480</wml2:value></wml2:MeasurementTVP></wml2:point>
<wml2:point><wml2:MeasurementTVP><wml2:time>2016-02-29T00:00:00+12:00</wml2:time><wml2:value>256471</wml2:value></wml2:MeasurementTVP></wml2:point>
<wml2:point><wml2:MeasurementTVP><wml2:time>2016-03-01T00:00:00+12:00</wml2:time><wml2:value>256496</wml2:value></wml2:MeasurementTVP></wml2:point>
<wml2:point><wml2:MeasurementTVP><wml2:time>2016-03-02T00:00:00+12:00</wml2:time><wml2:value>256491</wml2:value></wml2:MeasurementTVP></wml2:point>
<wml2:point><wml2:MeasurementTVP><wml2:time>2016-03-03T00:00:00+12:00</wml2:time><wml2:value>256479</wml2:value></wml2:MeasurementTVP></wml2:point>
<wml2:point><wml2:MeasurementTVP><wml2:time>2016-03-04T00:00:00+12:00</wml2:time><wml2:value>256474</wml2:value></wml2:MeasurementTVP></wml2:point>
<wml2:point><wml2:MeasurementTVP><wml2:time>2016-03-05T00:00:00+12:00</wml2:time><wml2:value>256467</wml2:value></wml2:MeasurementTVP></wml2:point>
<wml2:point><wml2:MeasurementTVP><wml2:time>2016-03-06T00:00:00+12:00</wml2:time><wml2:value>256465</wml2:value></wml2:MeasurementTVP></wml2:point>
<wml2:point><wml2:MeasurementTVP><wml2:time>2016-03-07T00:00:00+12:00</wml2:time><wml2:value>256466</wml2:value></wml2:MeasurementTVP></wml2:point>
<wml2:point><wml2:MeasurementTVP><wml2:time>2016-03-08T00:00:00+12:00</wml2:time><wml2:value>256468</wml2:value></wml2:MeasurementTVP></wml2:point>
<wml2:point><wml2:MeasurementTVP><wml2:time>2016-03-09T00:00:00+12:00</wml2:time><wml2:value>256620</wml2:value></wml2:MeasurementTVP></wml2:point>
<wml2:point><wml2:MeasurementTVP><wml2:time>2016-03-10T00:00:00+12:00</wml2:time><wml2:value>256695</wml2:value></wml2:MeasurementTVP></wml2:point>
<wml2:point><wml2:MeasurementTVP><wml2:time>2016-03-11T00:00:00+12:00</wml2:time><wml2:value>256553</wml2:value></wml2:MeasurementTVP></wml2:point>
<wml2:point><wml2:MeasurementTVP><wml2:time>2016-03-12T00:00:00+12:00</wml2:time><wml2:value>256774</wml2:value></wml2:MeasurementTVP></wml2:point>
<wml2:point><wml2:MeasurementTVP><wml2:time>2016-03-13T00:00:00+12:00</wml2:time><wml2:value>256571</wml2:value></wml2:MeasurementTVP></wml2:point>
<wml2:point><wml2:MeasurementTVP><wml2:time>2016-03-14T00:00:00+12:00</wml2:time><wml2:value>256533</wml2:value></wml2:MeasurementTVP></wml2:point>
<wml2:point><wml2:MeasurementTVP><wml2:time>2016-03-15T00:00:00+12:00</wml2:time><wml2:value>256517</wml2:value></wml2:MeasurementTVP></wml2:point>
<wml2:point><wml2:MeasurementTVP><wml2:time>2016-03-16T00:00:00+12:00</wml2:time><wml2:value>256515</wml2:value></wml2:MeasurementTVP></wml2:point>
<wml2:point><wml2:MeasurementTVP><wml2:time>2016-03-17T00:00:00+12:00</wml2:time><wml2:value>256591</wml2:value></wml2:MeasurementTVP></wml2:point>
<wml2:point><wml2:MeasurementTVP><wml2:time>2016-03-18T00:00:00+12:00</wml2:time><wml2:value>256686</wml2:value></wml2:MeasurementTVP></wml2:point>
<wml2:point><wml2:MeasurementTVP><wml2:time>2016-03-19T00:00:00+12:00</wml2:time><wml2:value>256738</wml2:value></wml2:MeasurementTVP></wml2:point>
<wml2:point><wml2:MeasurementTVP><wml2:time>2016-03-20T00:00:00+12:00</wml2:time><wml2:value>256619</wml2:value></wml2:MeasurementTVP></wml2:point>
<wml2:point><wml2:MeasurementTVP><wml2:time>2016-03-21T00:00:00+12:00</wml2:time><wml2:value>256573</wml2:value></wml2:MeasurementTVP></wml2:point>
<wml2:point><wml2:MeasurementTVP><wml2:time>2016-03-22T00:00:00+12:00</wml2:time><wml2:value>256547</wml2:value></wml2:MeasurementTVP></wml2:point>
<wml2:point><wml2:MeasurementTVP><wml2:time>2016-03-23T00:00:00+12:00</wml2:time><wml2:value>256530</wml2:value></wml2:MeasurementTVP></wml2:point>
<wml2:point><wml2:MeasurementTVP><wml2:time>2016-03-24T00:00:00+12:00</wml2:time><wml2:value>256519</wml2:value></wml2:MeasurementTVP></wml2:point>
<wml2:point><wml2:MeasurementTVP><wml2:time>2016-03-25T00:00:00+12:00</wml2:time><wml2:value>256650</wml2:value></wml2:MeasurementTVP></wml2:point>
<wml2:point><wml2:MeasurementTVP><wml2:time>2016-03-26T00:00:00+12:00</wml2:time><wml2:value>256641</wml2:value></wml2:MeasurementTVP></wml2:point>
<wml2:point><wml2:MeasurementTVP><wml2:time>2016-03-27T00:00:00+12:00</wml2:time><wml2:value>256570</wml2:value></wml2:MeasurementTVP></wml2:point>
<wml2:point><wml2:MeasurementTVP><wml2:time>2016-03-28T00:00:00+12:00</wml2:time><wml2:value>256547</wml2:value></wml2:MeasurementTVP></wml2:point>
<wml2:point><wml2:MeasurementTVP><wml2:time>2016-03-29T00:00:00+12:00</wml2:time><wml2:value>256532</wml2:value></wml2:MeasurementTVP></wml2:point>
<wml2:point><wml2:MeasurementTVP><wml2:time>2016-03-30T00:00:00+12:00</wml2:time><wml2:value>256521</wml2:value></wml2:MeasurementTVP></wml2:point>
<wml2:point><wml2:MeasurementTVP><wml2:time>2016-03-31T00:00:00+12:00</wml2:time><wml2:value>256510</wml2:value></wml2:MeasurementTVP></wml2:point>
<wml2:point><wml2:MeasurementTVP><wml2:time>2016-04-01T00:00:00+12:00</wml2:time><wml2:value>256504</wml2:value></wml2:MeasurementTVP></wml2:point>
<wml2:point><wml2:MeasurementTVP><wml2:time>2016-04-02T00:00:00+12:00</wml2:time><wml2:value>256498</wml2:value></wml2:MeasurementTVP></wml2:point>
<wml2:point><wml2:MeasurementTVP><wml2:time>2016-04-03T00:00:00+12:00</wml2:time><wml2:value>256545</wml2:value></wml2:MeasurementTVP></wml2:point>
<wml2:point><wml2:MeasurementTVP><wml2:time>2016-04-04T00:00:00+12:00</wml2:time><wml2:value>256843</wml2:value></wml2:MeasurementTVP></wml2:point>
<wml2:point><wml2:MeasurementTVP><wml2:time>2016-04-05T00:00:00+12:00</wml2:time><wml2:value>256770</wml2:value></wml2:MeasurementTVP></wml2:point>
<wml2:point><wml2:MeasurementTVP><wml2:time>2016-04-06T00:00:00+12:00</wml2:time><wml2:value>256647</wml2:value></wml2:MeasurementTVP></wml2:point>
<wml2:point><wml2:MeasurementTVP><wml2:time>2016-04-07T00:00:00+12:00</wml2:time><wml2:value>256592</wml2:value></wml2:MeasurementTVP></wml2:point>
<wml2:point><wml2:MeasurementTVP><wml2:time>2016-04-08T00:00:00+12:00</wml2:time><wml2:value>256564</wml2:value></wml2:MeasurementTVP></wml2:point>
<wml2:point><wml2:MeasurementTVP><wml2:time>2016-04-09T00:00:00+12:00</wml2:time><wml2:value>256633</wml2:value></wml2:MeasurementTVP></wml2:point>
<wml2:point><wml2:MeasurementTVP><wml2:time>2016-04-10T00:00:00+12:00</wml2:time><wml2:value>256613</wml2:value></wml2:MeasurementTVP></wml2:point>
<wml2:point><wml2:MeasurementTVP><wml2:time>2016-04-11T00:00:00+12:00</wml2:time><wml2:value>256587</wml2:value></wml2:MeasurementTVP></wml2:point>
<wml2:point><wml2:MeasurementTVP><wml2:time>2016-04-12T00:00:00+12:00</wml2:time><wml2:value>256594</wml2:value></wml2:MeasurementTVP></wml2:point>
<wml2:point><wml2:MeasurementTVP><wml2:time>2016-04-13T00:00:00+12:00</wml2:time><wml2:value>256637</wml2:value></wml2:MeasurementTVP></wml2:point>
<wml2:point><wml2:MeasurementTVP><wml2:time>2016-04-14T00:00:00+12:00</wml2:time><wml2:value>256659</wml2:value></wml2:MeasurementTVP></wml2:point>
<wml2:point><wml2:MeasurementTVP><wml2:time>2016-04-15T00:00:00+12:00</wml2:time><wml2:value>256589</wml2:value></wml2:MeasurementTVP></wml2:point>
<wml2:point><wml2:MeasurementTVP><wml2:time>2016-04-16T00:00:00+12:00</wml2:time><wml2:value>256563</wml2:value></wml2:MeasurementTVP></wml2:point>
<wml2:point><wml2:MeasurementTVP><wml2:time>2016-04-17T00:00:00+12:00</wml2:time><wml2:value>256546</wml2:value></wml2:MeasurementTVP></wml2:point>
<wml2:point><wml2:MeasurementTVP><wml2:time>2016-04-18T00:00:00+12:00</wml2:time><wml2:value>256533</wml2:value></wml2:MeasurementTVP></wml2:point>
<wml2:point><wml2:MeasurementTVP><wml2:time>2016-04-19T00:00:00+12:00</wml2:time><wml2:value>256525</wml2:value></wml2:MeasurementTVP></wml2:point>
<wml2:point><wml2:MeasurementTVP><wml2:time>2016-04-20T00:00:00+12:00</wml2:time><wml2:value>256518</wml2:value></wml2:MeasurementTVP></wml2:point>
<wml2:point><wml2:MeasurementTVP><wml2:time>2016-04-21T00:00:00+12:00</wml2:time><wml2:value>256511</wml2:value></wml2:MeasurementTVP></wml2:point>
<wml2:point><wml2:MeasurementTVP><wml2:time>2016-04-22T00:00:00+12:00</wml2:time><wml2:value>256505</wml2:value></wml2:MeasurementTVP></wml2:point>
<wml2:point><wml2:MeasurementTVP><wml2:time>2016-04-23T00:00:00+12:00</wml2:time><wml2:value>256501</wml2:value></wml2:MeasurementTVP></wml2:point>
<wml2:point><wml2:MeasurementTVP><wml2:time>2016-04-24T00:00:00+12:00</wml2:time><wml2:value>256498</wml2:value></wml2:MeasurementTVP></wml2:point>
<wml2:point><wml2:MeasurementTVP><wml2:time>2016-04-25T00:00:00+12:00</wml2:time><wml2:value>256664</wml2:value></wml2:MeasurementTVP></wml2:point>
<wml2:point><wml2:MeasurementTVP><wml2:time>2016-04-26T00:00:00+12:00</wml2:time><wml2:value>256571</wml2:value></wml2:MeasurementTVP></wml2:point>
<wml2:point><wml2:MeasurementTVP><wml2:time>2016-04-27T00:00:00+12:00</wml2:time><wml2:value>256532</wml2:value></wml2:MeasurementTVP></wml2:point>
<wml2:point><wml2:MeasurementTVP><wml2:time>2016-04-28T00:00:00+12:00</wml2:time><wml2:value>256516</wml2:value></wml2:MeasurementTVP></wml2:point>
<wml2:point><wml2:MeasurementTVP><wml2:time>2016-04-29T00:00:00+12:00</wml2:time><wml2:value>256507</wml2:value></wml2:MeasurementTVP></wml2:point>
<wml2:point><wml2:MeasurementTVP><wml2:time>2016-04-30T00:00:00+12:00</wml2:time><wml2:value>256500</wml2:value></wml2:MeasurementTVP></wml2:point>
<wml2:point><wml2:MeasurementTVP><wml2:time>2016-05-01T00:00:00+12:00</wml2:time><wml2:value>256495</wml2:value></wml2:MeasurementTVP></wml2:point>
<wml2:point><wml2:MeasurementTVP><wml2:time>2016-05-02T00:00:00+12:00</wml2:time><wml2:value>256491</wml2:value></wml2:MeasurementTVP></wml2:point>
<wml2:point><wml2:MeasurementTVP><wml2:time>2016-05-03T00:00:00+12:00</wml2:time><wml2:value>256487</wml2:value></wml2:MeasurementTVP></wml2:point>
<wml2:point><wml2:MeasurementTVP><wml2:time>2016-05-04T00:00:00+12:00</wml2:time><wml2:value>256848</wml2:value></wml2:MeasurementTVP></wml2:point>
<wml2:point><wml2:MeasurementTVP><wml2:time>2016-05-05T00:00:00+12:00</wml2:time><wml2:value>256862</wml2:value></wml2:MeasurementTVP></wml2:point>
<wml2:point><wml2:MeasurementTVP><wml2:time>2016-05-06T00:00:00+12:00</wml2:time><wml2:value>256920</wml2:value></wml2:MeasurementTVP></wml2:point>
<wml2:point><wml2:MeasurementTVP><wml2:time>2016-05-07T00:00:00+12:00</wml2:time><wml2:value>256802</wml2:value></wml2:MeasurementTVP></wml2:point>
<wml2:point><wml2:MeasurementTVP><wml2:time>2016-05-08T00:00:00+12:00</wml2:time><wml2:value>256673</wml2:value></wml2:MeasurementTVP></wml2:point>
<wml2:point><wml2:MeasurementTVP><wml2:time>2016-05-09T00:00:00+12:00</wml2:time><wml2:value>256623</wml2:value></wml2:MeasurementTVP></wml2:point>
<wml2:point><wml2:MeasurementTVP><wml2:time>2016-05-10T00:00:00+12:00</wml2:time><wml2:value>256594</wml2:value></wml2:MeasurementTVP></wml2:point>
<wml2:point><wml2:MeasurementTVP><wml2:time>2016-05-11T00:00:00+12:00</wml2:time><wml2:value>256574</wml2:value></wml2:MeasurementTVP></wml2:point>
<wml2:point><wml2:MeasurementTVP><wml2:time>2016-05-12T00:00:00+12:00</wml2:time><wml2:value>256566</wml2:value></wml2:MeasurementTVP></wml2:point>
<wml2:point><wml2:MeasurementTVP><wml2:time>2016-05-13T00:00:00+12:00</wml2:time><wml2:value>256959</wml2:value></wml2:MeasurementTVP></wml2:point>
<wml2:point><wml2:MeasurementTVP><wml2:time>2016-05-14T00:00:00+12:00</wml2:time><wml2:value>256783</wml2:value></wml2:MeasurementTVP></wml2:point>
<wml2:point><wml2:MeasurementTVP><wml2:time>2016-05-15T00:00:00+12:00</wml2:time><wml2:value>256880</wml2:value></wml2:MeasurementTVP></wml2:point>
<wml2:point><wml2:MeasurementTVP><wml2:time>2016-05-16T00:00:00+12:00</wml2:time><wml2:value>256714</wml2:value></wml2:MeasurementTVP></wml2:point>
<wml2:point><wml2:MeasurementTVP><wml2:time>2016-05-17T00:00:00+12:00</wml2:time><wml2:value>256778</wml2:value></wml2:MeasurementTVP></wml2:point>
<wml2:point><wml2:MeasurementTVP><wml2:time>2016-05-18T00:00:00+12:00</wml2:time><wml2:value>256952</wml2:value></wml2:MeasurementTVP></wml2:point>
<wml2:point><wml2:MeasurementTVP><wml2:time>2016-05-19T00:00:00+12:00</wml2:time><wml2:value>256906</wml2:value></wml2:MeasurementTVP></wml2:point>
<wml2:point><wml2:MeasurementTVP><wml2:time>2016-05-20T00:00:00+12:00</wml2:time><wml2:value>256823</wml2:value></wml2:MeasurementTVP></wml2:point>
<wml2:point><wml2:MeasurementTVP><wml2:time>2016-05-21T00:00:00+12:00</wml2:time><wml2:value>256910</wml2:value></wml2:MeasurementTVP></wml2:point>
<wml2:point><wml2:MeasurementTVP><wml2:time>2016-05-22T00:00:00+12:00</wml2:time><wml2:value>257249</wml2:value></wml2:MeasurementTVP></wml2:point>
<wml2:point><wml2:MeasurementTVP><wml2:time>2016-05-23T00:00:00+12:00</wml2:time><wml2:value>256879</wml2:value></wml2:MeasurementTVP></wml2:point>
<wml2:point><wml2:MeasurementTVP><wml2:time>2016-05-24T00:00:00+12:00</wml2:time><wml2:value>256849</wml2:value></wml2:MeasurementTVP></wml2:point>
<wml2:point><wml2:MeasurementTVP><wml2:time>2016-05-25T00:00:00+12:00</wml2:time><wml2:value>257314</wml2:value></wml2:MeasurementTVP></wml2:point>
<wml2:point><wml2:MeasurementTVP><wml2:time>2016-05-26T00:00:00+12:00</wml2:time><wml2:value>257617</wml2:value></wml2:MeasurementTVP></wml2:point>
<wml2:point><wml2:MeasurementTVP><wml2:time>2016-05-27T00:00:00+12:00</wml2:time><wml2:value>257436</wml2:value></wml2:MeasurementTVP></wml2:point>
<wml2:point><wml2:MeasurementTVP><wml2:time>2016-05-28T00:00:00+12:00</wml2:time><wml2:value>257137</wml2:value></wml2:MeasurementTVP></wml2:point>
<wml2:point><wml2:MeasurementTVP><wml2:time>2016-05-29T00:00:00+12:00</wml2:time><wml2:value>257398</wml2:value></wml2:MeasurementTVP></wml2:point>
<wml2:point><wml2:MeasurementTVP><wml2:time>2016-05-30T00:00:00+12:00</wml2:time><wml2:value>257194</wml2:value></wml2:MeasurementTVP></wml2:point>
<wml2:point><wml2:MeasurementTVP><wml2:time>2016-05-31T00:00:00+12:00</wml2:time><wml2:value>256954</wml2:value></wml2:MeasurementTVP></wml2:point>
<wml2:point><wml2:MeasurementTVP><wml2:time>2016-06-01T00:00:00+12:00</wml2:time><wml2:value>256843</wml2:value></wml2:MeasurementTVP></wml2:point>
<wml2:point><wml2:MeasurementTVP><wml2:time>2016-06-02T00:00:00+12:00</wml2:time><wml2:value>256765</wml2:value></wml2:MeasurementTVP></wml2:point>
<wml2:point><wml2:MeasurementTVP><wml2:time>2016-06-03T00:00:00+12:00</wml2:time><wml2:value>256712</wml2:value></wml2:MeasurementTVP></wml2:point>
<wml2:point><wml2:MeasurementTVP><wml2:time>2016-06-04T00:00:00+12:00</wml2:time><wml2:value>256675</wml2:value></wml2:MeasurementTVP></wml2:point>
<wml2:point><wml2:MeasurementTVP><wml2:time>2016-06-05T00:00:00+12:00</wml2:time><wml2:value>256647</wml2:value></wml2:MeasurementTVP></wml2:point>
<wml2:point><wml2:MeasurementTVP><wml2:time>2016-06-06T00:00:00+12:00</wml2:time><wml2:value>256624</wml2:value></wml2:MeasurementTVP></wml2:point>
<wml2:point><wml2:MeasurementTVP><wml2:time>2016-06-07T00:00:00+12:00</wml2:time><wml2:value>256606</wml2:value></wml2:MeasurementTVP></wml2:point>
<wml2:point><wml2:MeasurementTVP><wml2:time>2016-06-08T00:00:00+12:00</wml2:time><wml2:value>256591</wml2:value></wml2:MeasurementTVP></wml2:point>
<wml2:point><wml2:MeasurementTVP><wml2:time>2016-06-09T00:00:00+12:00</wml2:time><wml2:value>256579</wml2:value></wml2:MeasurementTVP></wml2:point>
<wml2:point><wml2:MeasurementTVP><wml2:time>2016-06-10T00:00:00+12:00</wml2:time><wml2:value>256571</wml2:value></wml2:MeasurementTVP></wml2:point>
<wml2:point><wml2:MeasurementTVP><wml2:time>2016-06-11T00:00:00+12:00</wml2:time><wml2:value>257045</wml2:value></wml2:MeasurementTVP></wml2:point>
<wml2:point><wml2:MeasurementTVP><wml2:time>2016-06-12T00:00:00+12:00</wml2:time><wml2:value>257060</wml2:value></wml2:MeasurementTVP></wml2:point>
<wml2:point><wml2:MeasurementTVP><wml2:time>2016-06-13T00:00:00+12:00</wml2:time><wml2:value>257045</wml2:value></wml2:MeasurementTVP></wml2:point>
<wml2:point><wml2:MeasurementTVP><wml2:time>2016-06-14T00:00:00+12:00</wml2:time><wml2:value>257006</wml2:value></wml2:MeasurementTVP></wml2:point>
<wml2:point><wml2:MeasurementTVP><wml2:time>2016-06-15T00:00:00+12:00</wml2:time><wml2:value>256800</wml2:value></wml2:MeasurementTVP></wml2:point>
<wml2:point><wml2:MeasurementTVP><wml2:time>2016-06-16T00:00:00+12:00</wml2:time><wml2:value>256731</wml2:value></wml2:MeasurementTVP></wml2:point>
<wml2:point><wml2:MeasurementTVP><wml2:time>2016-06-17T00:00:00+12:00</wml2:time><wml2:value>256776</wml2:value></wml2:MeasurementTVP></wml2:point>
<wml2:point><wml2:MeasurementTVP><wml2:time>2016-06-18T00:00:00+12:00</wml2:time><wml2:value>256682</wml2:value></wml2:MeasurementTVP></wml2:point>
<wml2:point><wml2:MeasurementTVP><wml2:time>2016-06-19T00:00:00+12:00</wml2:time><wml2:value>256652</wml2:value></wml2:MeasurementTVP></wml2:point>
<wml2:point><wml2:MeasurementTVP><wml2:time>2016-06-20T00:00:00+12:00</wml2:time><wml2:value>256709</wml2:value></wml2:MeasurementTVP></wml2:point>
<wml2:point><wml2:MeasurementTVP><wml2:time>2016-06-21T00:00:00+12:00</wml2:time><wml2:value>256657</wml2:value></wml2:MeasurementTVP></wml2:point>
<wml2:point><wml2:MeasurementTVP><wml2:time>2016-06-22T00:00:00+12:00</wml2:time><wml2:value>256666</wml2:value></wml2:MeasurementTVP></wml2:point>
<wml2:point><wml2:MeasurementTVP><wml2:time>2016-06-23T00:00:00+12:00</wml2:time><wml2:value>256664</wml2:value></wml2:MeasurementTVP></wml2:point>
<wml2:point><wml2:MeasurementTVP><wml2:time>2016-06-24T00:00:00+12:00</wml2:time><wml2:value>257017</wml2:value></wml2:MeasurementTVP></wml2:point>
<wml2:point><wml2:MeasurementTVP><wml2:time>2016-06-25T00:00:00+12:00</wml2:time><wml2:value>257115</wml2:value></wml2:MeasurementTVP></wml2:point>
<wml2:point><wml2:MeasurementTVP><wml2:time>2016-06-26T00:00:00+12:00</wml2:time><wml2:value>256852</wml2:value></wml2:MeasurementTVP></wml2:point>
<wml2:point><wml2:MeasurementTVP><wml2:time>2016-06-27T00:00:00+12:00</wml2:time><wml2:value>256849</wml2:value></wml2:MeasurementTVP></wml2:point>
<wml2:point><wml2:MeasurementTVP><wml2:time>2016-06-28T00:00:00+12:00</wml2:time><wml2:value>256849</wml2:value></wml2:MeasurementTVP></wml2:point>
<wml2:point><wml2:MeasurementTVP><wml2:time>2016-06-29T00:00:00+12:00</wml2:time><wml2:value>256973</wml2:value></wml2:MeasurementTVP></wml2:point>
<wml2:point><wml2:MeasurementTVP><wml2:time>2016-06-30T00:00:00+12:00</wml2:time><wml2:value>256832</wml2:value></wml2:MeasurementTVP></wml2:point>
<wml2:point><wml2:MeasurementTVP><wml2:time>2016-07-01T00:00:00+12:00</wml2:time><wml2:value>257081</wml2:value></wml2:MeasurementTVP></wml2:point>
<wml2:point><wml2:MeasurementTVP><wml2:time>2016-07-02T00:00:00+12:00</wml2:time><wml2:value>256851</wml2:value></wml2:MeasurementTVP></wml2:point>
<wml2:point><wml2:MeasurementTVP><wml2:time>2016-07-03T00:00:00+12:00</wml2:time><wml2:value>256761</wml2:value></wml2:MeasurementTVP></wml2:point>
<wml2:point><wml2:MeasurementTVP><wml2:time>2016-07-04T00:00:00+12:00</wml2:time><wml2:value>256740</wml2:value></wml2:MeasurementTVP></wml2:point>
<wml2:point><wml2:MeasurementTVP><wml2:time>2016-07-05T00:00:00+12:00</wml2:time><wml2:value>256682</wml2:value></wml2:MeasurementTVP></wml2:point>
<wml2:point><wml2:MeasurementTVP><wml2:time>2016-07-06T00:00:00+12:00</wml2:time><wml2:value>256745</wml2:value></wml2:MeasurementTVP></wml2:point>
<wml2:point><wml2:MeasurementTVP><wml2:time>2016-07-07T00:00:00+12:00</wml2:time><wml2:value>256680</wml2:value></wml2:MeasurementTVP></wml2:point>
<wml2:point><wml2:MeasurementTVP><wml2:time>2016-07-08T00:00:00+12:00</wml2:time><wml2:value>256647</wml2:value></wml2:MeasurementTVP></wml2:point>
<wml2:point><wml2:MeasurementTVP><wml2:time>2016-07-09T00:00:00+12:00</wml2:time><wml2:value>256825</wml2:value></wml2:MeasurementTVP></wml2:point>
<wml2:point><wml2:MeasurementTVP><wml2:time>2016-07-10T00:00:00+12:00</wml2:time><wml2:value>256828</wml2:value></wml2:MeasurementTVP></wml2:point>
<wml2:point><wml2:MeasurementTVP><wml2:time>2016-07-11T00:00:00+12:00</wml2:time><wml2:value>256740</wml2:value></wml2:MeasurementTVP></wml2:point>
<wml2:point><wml2:MeasurementTVP><wml2:time>2016-07-12T00:00:00+12:00</wml2:time><wml2:value>256692</wml2:value></wml2:MeasurementTVP></wml2:point>
<wml2:point><wml2:MeasurementTVP><wml2:time>2016-07-13T00:00:00+12:00</wml2:time><wml2:value>256658</wml2:value></wml2:MeasurementTVP></wml2:point>
<wml2:point><wml2:MeasurementTVP><wml2:time>2016-07-14T00:00:00+12:00</wml2:time><wml2:value>256634</wml2:value></wml2:MeasurementTVP></wml2:point>
<wml2:point><wml2:MeasurementTVP><wml2:time>2016-07-15T00:00:00+12:00</wml2:time><wml2:value>256981</wml2:value></wml2:MeasurementTVP></wml2:point>
<wml2:point><wml2:MeasurementTVP><wml2:time>2016-07-16T00:00:00+12:00</wml2:time><wml2:value>257244</wml2:value></wml2:MeasurementTVP></wml2:point>
<wml2:point><wml2:MeasurementTVP><wml2:time>2016-07-17T00:00:00+12:00</wml2:time><wml2:value>256955</wml2:value></wml2:MeasurementTVP></wml2:point>
<wml2:point><wml2:MeasurementTVP><wml2:time>2016-07-18T00:00:00+12:00</wml2:time><wml2:value>256818</wml2:value></wml2:MeasurementTVP></wml2:point>
<wml2:point><wml2:MeasurementTVP><wml2:time>2016-07-19T00:00:00+12:00</wml2:time><wml2:value>256750</wml2:value></wml2:MeasurementTVP></wml2:point>
<wml2:point><wml2:MeasurementTVP><wml2:time>2016-07-20T00:00:00+12:00</wml2:time><wml2:value>257222</wml2:value></wml2:MeasurementTVP></wml2:point>
<wml2:point><wml2:MeasurementTVP><wml2:time>2016-07-21T00:00:00+12:00</wml2:time><wml2:value>257250</wml2:value></wml2:MeasurementTVP></wml2:point>
<wml2:point><wml2:MeasurementTVP><wml2:time>2016-07-22T00:00:00+12:00</wml2:time><wml2:value>256874</wml2:value></wml2:MeasurementTVP></wml2:point>
<wml2:point><wml2:MeasurementTVP><wml2:time>2016-07-23T00:00:00+12:00</wml2:time><wml2:value>256776</wml2:value></wml2:MeasurementTVP></wml2:point>
<wml2:point><wml2:MeasurementTVP><wml2:time>2016-07-24T00:00:00+12:00</wml2:time><wml2:value>256757</wml2:value></wml2:MeasurementTVP></wml2:point>
<wml2:point><wml2:MeasurementTVP><wml2:time>2016-07-25T00:00:00+12:00</wml2:time><wml2:value>257223</wml2:value></wml2:MeasurementTVP></wml2:point>
<wml2:point><wml2:MeasurementTVP><wml2:time>2016-07-26T00:00:00+12:00</wml2:time><wml2:value>256969</wml2:value></wml2:MeasurementTVP></wml2:point>
<wml2:point><wml2:MeasurementTVP><wml2:time>2016-07-27T00:00:00+12:00</wml2:time><wml2:value>256864</wml2:value></wml2:MeasurementTVP></wml2:point>
<wml2:point><wml2:MeasurementTVP><wml2:time>2016-07-28T00:00:00+12:00</wml2:time><wml2:value>256804</wml2:value></wml2:MeasurementTVP></wml2:point>
<wml2:point><wml2:MeasurementTVP><wml2:time>2016-07-29T00:00:00+12:00</wml2:time><wml2:value>257517</wml2:value></wml2:MeasurementTVP></wml2:point>
<wml2:point><wml2:MeasurementTVP><wml2:time>2016-07-30T00:00:00+12:00</wml2:time><wml2:value>257228</wml2:value></wml2:MeasurementTVP></wml2:point>
<wml2:point><wml2:MeasurementTVP><wml2:time>2016-07-31T00:00:00+12:00</wml2:time><wml2:value>257116</wml2:value></wml2:MeasurementTVP></wml2:point>
<wml2:point><wml2:MeasurementTVP><wml2:time>2016-08-01T00:00:00+12:00</wml2:time><wml2:value>257056</wml2:value></wml2:MeasurementTVP></wml2:point>
<wml2:point><wml2:MeasurementTVP><wml2:time>2016-08-02T00:00:00+12:00</wml2:time><wml2:value>256908</wml2:value></wml2:MeasurementTVP></wml2:point>
<wml2:point><wml2:MeasurementTVP><wml2:time>2016-08-03T00:00:00+12:00</wml2:time><wml2:value>256857</wml2:value></wml2:MeasurementTVP></wml2:point>
<wml2:point><wml2:MeasurementTVP><wml2:time>2016-08-04T00:00:00+12:00</wml2:time><wml2:value>257190</wml2:value></wml2:MeasurementTVP></wml2:point>
<wml2:point><wml2:MeasurementTVP><wml2:time>2016-08-05T00:00:00+12:00</wml2:time><wml2:value>257384</wml2:value></wml2:MeasurementTVP></wml2:point>
<wml2:point><wml2:MeasurementTVP><wml2:time>2016-08-06T00:00:00+12:00</wml2:time><wml2:value>257023</wml2:value></wml2:MeasurementTVP></wml2:point>
<wml2:point><wml2:MeasurementTVP><wml2:time>2016-08-07T00:00:00+12:00</wml2:time><wml2:value>257194</wml2:value></wml2:MeasurementTVP></wml2:point>
<wml2:point><wml2:MeasurementTVP><wml2:time>2016-08-08T00:00:00+12:00</wml2:time><wml2:value>256953</wml2:value></wml2:MeasurementTVP></wml2:point>
<wml2:point><wml2:MeasurementTVP><wml2:time>2016-08-09T00:00:00+12:00</wml2:time><wml2:value>256824</wml2:value></wml2:MeasurementTVP></wml2:point>
<wml2:point><wml2:MeasurementTVP><wml2:time>2016-08-10T00:00:00+12:00</wml2:time><wml2:value>256752</wml2:value></wml2:MeasurementTVP></wml2:point>
<wml2:point><wml2:MeasurementTVP><wml2:time>2016-08-11T00:00:00+12:00</wml2:time><wml2:value>256709</wml2:value></wml2:MeasurementTVP></wml2:point>
<wml2:point><wml2:MeasurementTVP><wml2:time>2016-08-12T00:00:00+12:00</wml2:time><wml2:value>256688</wml2:value></wml2:MeasurementTVP></wml2:point>
<wml2:point><wml2:MeasurementTVP><wml2:time>2016-08-13T00:00:00+12:00</wml2:time><wml2:value>256675</wml2:value></wml2:MeasurementTVP></wml2:point>
<wml2:point><wml2:MeasurementTVP><wml2:time>2016-08-14T00:00:00+12:00</wml2:time><wml2:value>257156</wml2:value></wml2:MeasurementTVP></wml2:point>
<wml2:point><wml2:MeasurementTVP><wml2:time>2016-08-15T00:00:00+12:00</wml2:time><wml2:value>256901</wml2:value></wml2:MeasurementTVP></wml2:point>
<wml2:point><wml2:MeasurementTVP><wml2:time>2016-08-16T00:00:00+12:00</wml2:time><wml2:value>256769</wml2:value></wml2:MeasurementTVP></wml2:point>
<wml2:point><wml2:MeasurementTVP><wml2:time>2016-08-17T00:00:00+12:00</wml2:time><wml2:value>256708</wml2:value></wml2:MeasurementTVP></wml2:point>
<wml2:point><wml2:MeasurementTVP><wml2:time>2016-08-18T00:00:00+12:00</wml2:time><wml2:value>256669</wml2:value></wml2:MeasurementTVP></wml2:point>
<wml2:point><wml2:MeasurementTVP><wml2:time>2016-08-19T00:00:00+12:00</wml2:time><wml2:value>256642</wml2:value></wml2:MeasurementTVP></wml2:point>
<wml2:point><wml2:MeasurementTVP><wml2:time>2016-08-20T00:00:00+12:00</wml2:time><wml2:value>256620</wml2:value></wml2:MeasurementTVP></wml2:point>
<wml2:point><wml2:MeasurementTVP><wml2:time>2016-08-21T00:00:00+12:00</wml2:time><wml2:value>256606</wml2:value></wml2:MeasurementTVP></wml2:point>
<wml2:point><wml2:MeasurementTVP><wml2:time>2016-08-22T00:00:00+12:00</wml2:time><wml2:value>256590</wml2:value></wml2:MeasurementTVP></wml2:point>
<wml2:point><wml2:MeasurementTVP><wml2:time>2016-08-23T00:00:00+12:00</wml2:time><wml2:value>256580</wml2:value></wml2:MeasurementTVP></wml2:point>
<wml2:point><wml2:MeasurementTVP><wml2:time>2016-08-24T00:00:00+12:00</wml2:time><wml2:value>256623</wml2:value></wml2:MeasurementTVP></wml2:point>
<wml2:point><wml2:MeasurementTVP><wml2:time>2016-08-25T00:00:00+12:00</wml2:time><wml2:value>256579</wml2:value></wml2:MeasurementTVP></wml2:point>
<wml2:point><wml2:MeasurementTVP><wml2:time>2016-08-26T00:00:00+12:00</wml2:time><wml2:value>256714</wml2:value></wml2:MeasurementTVP></wml2:point>
<wml2:point><wml2:MeasurementTVP><wml2:time>2016-08-27T00:00:00+12:00</wml2:time><wml2:value>256896</wml2:value></wml2:MeasurementTVP></wml2:point>
<wml2:point><wml2:MeasurementTVP><wml2:time>2016-08-28T00:00:00+12:00</wml2:time><wml2:value>257123</wml2:value></wml2:MeasurementTVP></wml2:point>
<wml2:point><wml2:MeasurementTVP><wml2:time>2016-08-29T00:00:00+12:00</wml2:time><wml2:value>256796</wml2:value></wml2:MeasurementTVP></wml2:point>
<wml2:point><wml2:MeasurementTVP><wml2:time>2016-08-30T00:00:00+12:00</wml2:time><wml2:value>256717</wml2:value></wml2:MeasurementTVP></wml2:point>
<wml2:point><wml2:MeasurementTVP><wml2:time>2016-08-31T00:00:00+12:00</wml2:time><wml2:value>256668</wml2:value></wml2:MeasurementTVP></wml2:point>
<wml2:point><wml2:MeasurementTVP><wml2:time>2016-09-01T00:00:00+12:00</wml2:time><wml2:value>256637</wml2:value></wml2:MeasurementTVP></wml2:point>
<wml2:point><wml2:MeasurementTVP><wml2:time>2016-09-02T00:00:00+12:00</wml2:time><wml2:value>256613</wml2:value></wml2:MeasurementTVP></wml2:point>
<wml2:point><wml2:MeasurementTVP><wml2:time>2016-09-03T00:00:00+12:00</wml2:time><wml2:value>256790</wml2:value></wml2:MeasurementTVP></wml2:point>
<wml2:point><wml2:MeasurementTVP><wml2:time>2016-09-04T00:00:00+12:00</wml2:time><wml2:value>256840</wml2:value></wml2:MeasurementTVP></wml2:point>
<wml2:point><wml2:MeasurementTVP><wml2:time>2016-09-05T00:00:00+12:00</wml2:time><wml2:value>256840</wml2:value></wml2:MeasurementTVP></wml2:point>
<wml2:point><wml2:MeasurementTVP><wml2:time>2016-09-06T00:00:00+12:00</wml2:time><wml2:value>257498</wml2:value></wml2:MeasurementTVP></wml2:point>
<wml2:point><wml2:MeasurementTVP><wml2:time>2016-09-07T00:00:00+12:00</wml2:time><wml2:value>257021</wml2:value></wml2:MeasurementTVP></wml2:point>
<wml2:point><wml2:MeasurementTVP><wml2:time>2016-09-08T00:00:00+12:00</wml2:time><wml2:value>256961</wml2:value></wml2:MeasurementTVP></wml2:point>
<wml2:point><wml2:MeasurementTVP><wml2:time>2016-09-09T00:00:00+12:00</wml2:time><wml2:value>256895</wml2:value></wml2:MeasurementTVP></wml2:point>
<wml2:point><wml2:MeasurementTVP><wml2:time>2016-09-10T00:00:00+12:00</wml2:time><wml2:value>256855</wml2:value></wml2:MeasurementTVP></wml2:point>
<wml2:point><wml2:MeasurementTVP><wml2:time>2016-09-11T00:00:00+12:00</wml2:time><wml2:value>256828</wml2:value></wml2:MeasurementTVP></wml2:point>
<wml2:point><wml2:MeasurementTVP><wml2:time>2016-09-12T00:00:00+12:00</wml2:time><wml2:value>256756</wml2:value></wml2:MeasurementTVP></wml2:point>
<wml2:point><wml2:MeasurementTVP><wml2:time>2016-09-13T00:00:00+12:00</wml2:time><wml2:value>256699</wml2:value></wml2:MeasurementTVP></wml2:point>
<wml2:point><wml2:MeasurementTVP><wml2:time>2016-09-14T00:00:00+12:00</wml2:time><wml2:value>256754</wml2:value></wml2:MeasurementTVP></wml2:point>
<wml2:point><wml2:MeasurementTVP><wml2:time>2016-09-15T00:00:00+12:00</wml2:time><wml2:value>256766</wml2:value></wml2:MeasurementTVP></wml2:point>
<wml2:point><wml2:MeasurementTVP><wml2:time>2016-09-16T00:00:00+12:00</wml2:time><wml2:value>256673</wml2:value></wml2:MeasurementTVP></wml2:point>
<wml2:point><wml2:MeasurementTVP><wml2:time>2016-09-17T00:00:00+12:00</wml2:time><wml2:value>257122</wml2:value></wml2:MeasurementTVP></wml2:point>
<wml2:point><wml2:MeasurementTVP><wml2:time>2016-09-18T00:00:00+12:00</wml2:time><wml2:value>257502</wml2:value></wml2:MeasurementTVP></wml2:point>
<wml2:point><wml2:MeasurementTVP><wml2:time>2016-09-19T00:00:00+12:00</wml2:time><wml2:value>257387</wml2:value></wml2:MeasurementTVP></wml2:point>
<wml2:point><wml2:MeasurementTVP><wml2:time>2016-09-20T00:00:00+12:00</wml2:time><wml2:value>256922</wml2:value></wml2:MeasurementTVP></wml2:point>
<wml2:point><wml2:MeasurementTVP><wml2:time>2016-09-21T00:00:00+12:00</wml2:time><wml2:value>256792</wml2:value></wml2:MeasurementTVP></wml2:point>
<wml2:point><wml2:MeasurementTVP><wml2:time>2016-09-22T00:00:00+12:00</wml2:time><wml2:value>256723</wml2:value></wml2:MeasurementTVP></wml2:point>
<wml2:point><wml2:MeasurementTVP><wml2:time>2016-09-23T00:00:00+12:00</wml2:time><wml2:value>256679</wml2:value></wml2:MeasurementTVP></wml2:point>
<wml2:point><wml2:MeasurementTVP><wml2:time>2016-09-24T00:00:00+12:00</wml2:time><wml2:value>256648</wml2:value></wml2:MeasurementTVP></wml2:point>
<wml2:point><wml2:MeasurementTVP><wml2:time>2016-09-25T00:00:00+12:00</wml2:time><wml2:value>256624</wml2:value></wml2:MeasurementTVP></wml2:point>
<wml2:point><wml2:MeasurementTVP><wml2:time>2016-09-26T00:00:00+12:00</wml2:time><wml2:value>256646</wml2:value></wml2:MeasurementTVP></wml2:point>
<wml2:point><wml2:MeasurementTVP><wml2:time>2016-09-27T00:00:00+12:00</wml2:time><wml2:value>256660</wml2:value></wml2:MeasurementTVP></wml2:point>
<wml2:point><wml2:MeasurementTVP><wml2:time>2016-09-28T00:00:00+12:00</wml2:time><wml2:value>256671</wml2:value></wml2:MeasurementTVP></wml2:point>
<wml2:point><wml2:MeasurementTVP><wml2:time>2016-09-29T00:00:00+12:00</wml2:time><wml2:value>256705</wml2:value></wml2:MeasurementTVP></wml2:point>
<wml2:point><wml2:MeasurementTVP><wml2:time>2016-09-30T00:00:00+12:00</wml2:time><wml2:value>256745</wml2:value></wml2:MeasurementTVP></wml2:point>
<wml2:point><wml2:MeasurementTVP><wml2:time>2016-10-01T00:00:00+12:00</wml2:time><wml2:value>256676</wml2:value></wml2:MeasurementTVP></wml2:point>
</wml2:MeasurementTimeseries></om:result></om:OM_Observation></wml2:observationMember>
</wml2:Collection>
