{
  "@context": ["https://opengeospatial.github.io/ELFIE/json-ld/elf-index.jsonld", "https://opengeospatial.github.io/ELFIE/json-ld/hyf.jsonld", "http://geojson.org/geojson-ld/geojson-context.jsonld"],
  "@id": "https://opengeospatial.github.io/ELFIE/usgs/huc12pp/uswb/031601130201",
  "@type": "http://www.opengeospatial.org/standards/waterml2/hy_features/HY_HydroNexus",
  "name": "Outlet of Mill Creek-Black Warrior River",
  "description": "comment describing the outlet of each watershed",
  "contributingCatchment": "https://opengeospatial.github.io/ELFIE/usgs/huc12/uswb/031601130201",
  "nexusRealization": "https://opengeospatial.github.io/ELFIE/usgs/uswb/nwissite/02465000",
  "geo": {
    "@type": "schema:GeoCoordinates",
    "latitude": 33.2065,
    "longitude": -87.6005
  }
}
