{
  "@context": ["https://opengeospatial.github.io/ELFIE/json-ld/elf-index.jsonld", "https://opengeospatial.github.io/ELFIE/json-ld/hyf.jsonld", "http://geojson.org/geojson-ld/geojson-context.jsonld"],
  "@id": "https://opengeospatial.github.io/ELFIE/tx/flowlines/floodcast/FS_BuffaloBayou",
  "@type": "http://www.opengeospatial.org/standards/waterml2/hy_features/HY_Flowpath",
  "name": "Buffalo Bayou at State Hwy 6 nr Addicks, TX",
  "description": "This is the flowline for the gage used to model the floodplains for the harvey huricane event in this area of interest.",
  "realizedCatchment": "https://opengeospatial.github.io/ELFIE/usgs/huc10/floodcast/1204010403",
  "geo": {
    "@type": "schema:GeoShape",
    "schema:line": {
      "@type": "Feature",
      "geometry": {
        "@type": "MultiLineString",
        "coordinates": [
          [
            [
              [-95.432, 29.7598, 0],
              [-95.431, 29.7588, 0],
              [-95.4303, 29.7585, 0],
              [-95.4293, 29.7583, 0],
              [-95.429, 29.7584, 0],
              [-95.4285, 29.7588, 0],
              [-95.4285, 29.7593, 0],
              [-95.4293, 29.7601, 0],
              [-95.4293, 29.7605, 0],
              [-95.4289, 29.7606, 0],
              [-95.4277, 29.7604, 0],
              [-95.4273, 29.7598, 0],
              [-95.4272, 29.7592, 0],
              [-95.4271, 29.759, 0],
              [-95.4271, 29.7589, 0],
              [-95.4268, 29.7585, 0],
              [-95.4262, 29.7584, 0],
              [-95.4259, 29.758, 0],
              [-95.4256, 29.7572, 0],
              [-95.4253, 29.7567, 0],
              [-95.4248, 29.7567, 0],
              [-95.4246, 29.7569, 0],
              [-95.4244, 29.7576, 0],
              [-95.424, 29.7584, 0],
              [-95.4235, 29.7584, 0],
              [-95.423, 29.7581, 0],
              [-95.4229, 29.7578, 0],
              [-95.4225, 29.7575, 0],
              [-95.422, 29.7576, 0],
              [-95.4218, 29.7577, 0],
              [-95.4212, 29.7582, 0],
              [-95.421, 29.7586, 0],
              [-95.4203, 29.7593, 0],
              [-95.42, 29.7593, 0],
              [-95.4193, 29.7587, 0],
              [-95.419, 29.7583, 0],
              [-95.419, 29.758, 0],
              [-95.4187, 29.7577, 0],
              [-95.4185, 29.7576, 0],
              [-95.4181, 29.7577, 0],
              [-95.4172, 29.7586, 0],
              [-95.4165, 29.7595, 0],
              [-95.4161, 29.7601, 0],
              [-95.4159, 29.7602, 0],
              [-95.4155, 29.7602, 0],
              [-95.4147, 29.7599, 0],
              [-95.4139, 29.7599, 0],
              [-95.4136, 29.76, 0],
              [-95.4133, 29.7604, 0],
              [-95.4132, 29.7617, 0],
              [-95.4131, 29.7621, 0],
              [-95.4128, 29.7623, 0],
              [-95.4117, 29.762, 0],
              [-95.4094, 29.7608, 0],
              [-95.4088, 29.7606, 0],
              [-95.408, 29.7606, 0],
              [-95.4068, 29.7609, 0],
              [-95.4044, 29.7609, 0],
              [-95.4032, 29.7612, 0],
              [-95.4026, 29.7614, 0],
              [-95.4023, 29.7617, 0],
              [-95.4015, 29.7619, 0],
              [-95.4003, 29.762, 0],
              [-95.3989, 29.7618, 0],
              [-95.3976, 29.7621, 0],
              [-95.3958, 29.7629, 0],
              [-95.3951, 29.763, 0],
              [-95.3932, 29.7626, 0],
              [-95.3915, 29.7626, 0],
              [-95.389, 29.7619, 0],
              [-95.3879, 29.7617, 0],
              [-95.3863, 29.7616, 0],
              [-95.3849, 29.7617, 0],
              [-95.3846, 29.7619, 0],
              [-95.3845, 29.7624, 0],
              [-95.384, 29.7633, 0],
              [-95.3834, 29.7637, 0],
              [-95.3829, 29.7638, 0],
              [-95.3825, 29.7637, 0],
              [-95.3821, 29.7633, 0],
              [-95.3815, 29.7623, 0],
              [-95.3812, 29.7622, 0],
              [-95.3805, 29.7621, 0],
              [-95.3799, 29.7623, 0],
              [-95.3789, 29.7623, 0],
              [-95.3785, 29.7622, 0],
              [-95.3779, 29.7618, 0],
              [-95.3773, 29.7613, 0],
              [-95.3767, 29.7612, 0],
              [-95.3763, 29.7611, 0],
              [-95.3752, 29.7613, 0],
              [-95.3745, 29.7614, 0],
              [-95.3736, 29.7612, 0],
              [-95.3728, 29.7613, 0],
              [-95.3721, 29.7617, 0],
              [-95.3715, 29.762, 0],
              [-95.3705, 29.7631, 0],
              [-95.3698, 29.7634, 0],
              [-95.3681, 29.7633, 0],
              [-95.3672, 29.7633, 0],
              [-95.3669, 29.7635, 0],
              [-95.3659, 29.7645, 0],
              [-95.3656, 29.7646, 0],
              [-95.3647, 29.7646, 0],
              [-95.3635, 29.7644, 0],
              [-95.363, 29.7644, 0],
              [-95.3617, 29.7649, 0],
              [-95.361, 29.765, 0],
              [-95.3595, 29.765, 0],
              [-95.3586, 29.7648, 0]
            ],
            [
              [-95.4595, 29.762, 0],
              [-95.4591, 29.762, 0],
              [-95.4582, 29.7617, 0],
              [-95.4579, 29.7615, 0],
              [-95.4579, 29.7608, 0],
              [-95.4581, 29.7604, 0],
              [-95.4581, 29.76, 0],
              [-95.4579, 29.7596, 0],
              [-95.4575, 29.7595, 0],
              [-95.4568, 29.7596, 0],
              [-95.456, 29.76, 0],
              [-95.4553, 29.76, 0],
              [-95.453, 29.7589, 0],
              [-95.4526, 29.7586, 0],
              [-95.4526, 29.7582, 0],
              [-95.4529, 29.7578, 0],
              [-95.4529, 29.7574, 0],
              [-95.4517, 29.7573, 0],
              [-95.4513, 29.7571, 0],
              [-95.4512, 29.7568, 0],
              [-95.4509, 29.7566, 0],
              [-95.4506, 29.7564, 0],
              [-95.4485, 29.7561, 0],
              [-95.447, 29.7556, 0],
              [-95.4466, 29.7553, 0],
              [-95.4464, 29.7549, 0],
              [-95.4464, 29.7544, 0],
              [-95.4462, 29.7541, 0],
              [-95.4457, 29.754, 0],
              [-95.4436, 29.7541, 0],
              [-95.4427, 29.7536, 0],
              [-95.4422, 29.7537, 0],
              [-95.4416, 29.7543, 0],
              [-95.4411, 29.7553, 0],
              [-95.4402, 29.756, 0],
              [-95.44, 29.7566, 0],
              [-95.4398, 29.7569, 0],
              [-95.439, 29.7571, 0],
              [-95.4386, 29.757, 0],
              [-95.4381, 29.757, 0],
              [-95.438, 29.7572, 0],
              [-95.438, 29.7575, 0],
              [-95.4382, 29.7578, 0],
              [-95.4391, 29.7586, 0],
              [-95.4392, 29.759, 0],
              [-95.4391, 29.7593, 0],
              [-95.4388, 29.7596, 0],
              [-95.4382, 29.7597, 0],
              [-95.438, 29.7596, 0],
              [-95.4362, 29.7584, 0],
              [-95.4356, 29.758, 0],
              [-95.4345, 29.7579, 0],
              [-95.4342, 29.7578, 0],
              [-95.4337, 29.7576, 0],
              [-95.4333, 29.7579, 0],
              [-95.4332, 29.7581, 0],
              [-95.4333, 29.7597, 0],
              [-95.433, 29.7599, 0],
              [-95.4323, 29.7599, 0],
              [-95.432, 29.7598, 0]
            ],
            [
              [-95.432, 29.7598, 0],
              [-95.431, 29.7588, 0],
              [-95.4303, 29.7585, 0],
              [-95.4293, 29.7583, 0],
              [-95.429, 29.7584, 0],
              [-95.4285, 29.7588, 0],
              [-95.4285, 29.7593, 0],
              [-95.4293, 29.7601, 0],
              [-95.4293, 29.7605, 0],
              [-95.4289, 29.7606, 0],
              [-95.4277, 29.7604, 0],
              [-95.4273, 29.7598, 0],
              [-95.4272, 29.7592, 0],
              [-95.4271, 29.759, 0],
              [-95.4271, 29.7589, 0],
              [-95.4268, 29.7585, 0],
              [-95.4262, 29.7584, 0],
              [-95.4259, 29.758, 0],
              [-95.4256, 29.7572, 0],
              [-95.4253, 29.7567, 0],
              [-95.4248, 29.7567, 0],
              [-95.4246, 29.7569, 0],
              [-95.4244, 29.7576, 0],
              [-95.424, 29.7584, 0],
              [-95.4235, 29.7584, 0],
              [-95.423, 29.7581, 0],
              [-95.4229, 29.7578, 0],
              [-95.4225, 29.7575, 0],
              [-95.422, 29.7576, 0],
              [-95.4218, 29.7577, 0],
              [-95.4212, 29.7582, 0],
              [-95.421, 29.7586, 0],
              [-95.4203, 29.7593, 0],
              [-95.42, 29.7593, 0],
              [-95.4193, 29.7587, 0],
              [-95.419, 29.7583, 0],
              [-95.419, 29.758, 0],
              [-95.4187, 29.7577, 0],
              [-95.4185, 29.7576, 0],
              [-95.4181, 29.7577, 0],
              [-95.4172, 29.7586, 0],
              [-95.4165, 29.7595, 0],
              [-95.4161, 29.7601, 0],
              [-95.4159, 29.7602, 0],
              [-95.4155, 29.7602, 0],
              [-95.4147, 29.7599, 0],
              [-95.4139, 29.7599, 0],
              [-95.4136, 29.76, 0],
              [-95.4133, 29.7604, 0],
              [-95.4132, 29.7617, 0],
              [-95.4131, 29.7621, 0],
              [-95.4128, 29.7623, 0],
              [-95.4117, 29.762, 0],
              [-95.4094, 29.7608, 0],
              [-95.4088, 29.7606, 0],
              [-95.408, 29.7606, 0],
              [-95.4068, 29.7609, 0],
              [-95.4044, 29.7609, 0],
              [-95.4032, 29.7612, 0],
              [-95.4026, 29.7614, 0],
              [-95.4023, 29.7617, 0],
              [-95.4015, 29.7619, 0],
              [-95.4003, 29.762, 0],
              [-95.3989, 29.7618, 0],
              [-95.3976, 29.7621, 0],
              [-95.3958, 29.7629, 0],
              [-95.3951, 29.763, 0],
              [-95.3932, 29.7626, 0],
              [-95.3915, 29.7626, 0],
              [-95.389, 29.7619, 0],
              [-95.3879, 29.7617, 0],
              [-95.3863, 29.7616, 0],
              [-95.3849, 29.7617, 0],
              [-95.3846, 29.7619, 0],
              [-95.3845, 29.7624, 0],
              [-95.384, 29.7633, 0],
              [-95.3834, 29.7637, 0],
              [-95.3829, 29.7638, 0],
              [-95.3825, 29.7637, 0],
              [-95.3821, 29.7633, 0],
              [-95.3815, 29.7623, 0],
              [-95.3812, 29.7622, 0],
              [-95.3805, 29.7621, 0],
              [-95.3799, 29.7623, 0],
              [-95.3789, 29.7623, 0],
              [-95.3785, 29.7622, 0],
              [-95.3779, 29.7618, 0],
              [-95.3773, 29.7613, 0],
              [-95.3767, 29.7612, 0],
              [-95.3763, 29.7611, 0],
              [-95.3752, 29.7613, 0],
              [-95.3745, 29.7614, 0],
              [-95.3736, 29.7612, 0],
              [-95.3728, 29.7613, 0],
              [-95.3721, 29.7617, 0],
              [-95.3715, 29.762, 0],
              [-95.3705, 29.7631, 0],
              [-95.3698, 29.7634, 0],
              [-95.3681, 29.7633, 0],
              [-95.3672, 29.7633, 0],
              [-95.3669, 29.7635, 0],
              [-95.3659, 29.7645, 0],
              [-95.3656, 29.7646, 0],
              [-95.3647, 29.7646, 0],
              [-95.3635, 29.7644, 0],
              [-95.363, 29.7644, 0],
              [-95.3617, 29.7649, 0],
              [-95.361, 29.765, 0],
              [-95.3595, 29.765, 0],
              [-95.3586, 29.7648, 0]
            ],
            [
              [-95.4691, 29.7707, 0],
              [-95.4683, 29.7707, 0],
              [-95.4681, 29.7701, 0],
              [-95.467, 29.7689, 0],
              [-95.4665, 29.7687, 0],
              [-95.466, 29.7686, 0],
              [-95.4655, 29.7688, 0],
              [-95.4651, 29.7689, 0],
              [-95.4649, 29.7688, 0],
              [-95.4649, 29.7682, 0],
              [-95.4651, 29.7671, 0],
              [-95.4649, 29.7669, 0],
              [-95.4644, 29.767, 0],
              [-95.4638, 29.7675, 0],
              [-95.4633, 29.7677, 0],
              [-95.4625, 29.7677, 0],
              [-95.4623, 29.7675, 0],
              [-95.462, 29.7664, 0],
              [-95.4619, 29.7662, 0],
              [-95.4611, 29.7659, 0],
              [-95.4605, 29.7654, 0],
              [-95.4603, 29.7653, 0],
              [-95.4591, 29.7652, 0],
              [-95.4582, 29.7645, 0],
              [-95.458, 29.7642, 0],
              [-95.458, 29.7638, 0],
              [-95.4582, 29.7633, 0],
              [-95.4587, 29.7629, 0],
              [-95.4593, 29.7628, 0],
              [-95.4605, 29.7629, 0],
              [-95.4607, 29.7628, 0],
              [-95.4607, 29.7625, 0],
              [-95.4605, 29.7624, 0],
              [-95.4596, 29.7622, 0],
              [-95.4595, 29.762, 0]
            ],
            [
              [-95.4595, 29.762, 0],
              [-95.4591, 29.762, 0],
              [-95.4582, 29.7617, 0],
              [-95.4579, 29.7615, 0],
              [-95.4579, 29.7608, 0],
              [-95.4581, 29.7604, 0],
              [-95.4581, 29.76, 0],
              [-95.4579, 29.7596, 0],
              [-95.4575, 29.7595, 0],
              [-95.4568, 29.7596, 0],
              [-95.456, 29.76, 0],
              [-95.4553, 29.76, 0],
              [-95.453, 29.7589, 0],
              [-95.4526, 29.7586, 0],
              [-95.4526, 29.7582, 0],
              [-95.4529, 29.7578, 0],
              [-95.4529, 29.7574, 0],
              [-95.4517, 29.7573, 0],
              [-95.4513, 29.7571, 0],
              [-95.4512, 29.7568, 0],
              [-95.4509, 29.7566, 0],
              [-95.4506, 29.7564, 0],
              [-95.4485, 29.7561, 0],
              [-95.447, 29.7556, 0],
              [-95.4466, 29.7553, 0],
              [-95.4464, 29.7549, 0],
              [-95.4464, 29.7544, 0],
              [-95.4462, 29.7541, 0],
              [-95.4457, 29.754, 0],
              [-95.4436, 29.7541, 0],
              [-95.4427, 29.7536, 0],
              [-95.4422, 29.7537, 0],
              [-95.4416, 29.7543, 0],
              [-95.4411, 29.7553, 0],
              [-95.4402, 29.756, 0],
              [-95.44, 29.7566, 0],
              [-95.4398, 29.7569, 0],
              [-95.439, 29.7571, 0],
              [-95.4386, 29.757, 0],
              [-95.4381, 29.757, 0],
              [-95.438, 29.7572, 0],
              [-95.438, 29.7575, 0],
              [-95.4382, 29.7578, 0],
              [-95.4391, 29.7586, 0],
              [-95.4392, 29.759, 0],
              [-95.4391, 29.7593, 0],
              [-95.4388, 29.7596, 0],
              [-95.4382, 29.7597, 0],
              [-95.438, 29.7596, 0],
              [-95.4362, 29.7584, 0],
              [-95.4356, 29.758, 0],
              [-95.4345, 29.7579, 0],
              [-95.4342, 29.7578, 0],
              [-95.4337, 29.7576, 0],
              [-95.4333, 29.7579, 0],
              [-95.4332, 29.7581, 0],
              [-95.4333, 29.7597, 0],
              [-95.433, 29.7599, 0],
              [-95.4323, 29.7599, 0],
              [-95.432, 29.7598, 0]
            ],
            [
              [-95.432, 29.7598, 0],
              [-95.431, 29.7588, 0],
              [-95.4303, 29.7585, 0],
              [-95.4293, 29.7583, 0],
              [-95.429, 29.7584, 0],
              [-95.4285, 29.7588, 0],
              [-95.4285, 29.7593, 0],
              [-95.4293, 29.7601, 0],
              [-95.4293, 29.7605, 0],
              [-95.4289, 29.7606, 0],
              [-95.4277, 29.7604, 0],
              [-95.4273, 29.7598, 0],
              [-95.4272, 29.7592, 0],
              [-95.4271, 29.759, 0],
              [-95.4271, 29.7589, 0],
              [-95.4268, 29.7585, 0],
              [-95.4262, 29.7584, 0],
              [-95.4259, 29.758, 0],
              [-95.4256, 29.7572, 0],
              [-95.4253, 29.7567, 0],
              [-95.4248, 29.7567, 0],
              [-95.4246, 29.7569, 0],
              [-95.4244, 29.7576, 0],
              [-95.424, 29.7584, 0],
              [-95.4235, 29.7584, 0],
              [-95.423, 29.7581, 0],
              [-95.4229, 29.7578, 0],
              [-95.4225, 29.7575, 0],
              [-95.422, 29.7576, 0],
              [-95.4218, 29.7577, 0],
              [-95.4212, 29.7582, 0],
              [-95.421, 29.7586, 0],
              [-95.4203, 29.7593, 0],
              [-95.42, 29.7593, 0],
              [-95.4193, 29.7587, 0],
              [-95.419, 29.7583, 0],
              [-95.419, 29.758, 0],
              [-95.4187, 29.7577, 0],
              [-95.4185, 29.7576, 0],
              [-95.4181, 29.7577, 0],
              [-95.4172, 29.7586, 0],
              [-95.4165, 29.7595, 0],
              [-95.4161, 29.7601, 0],
              [-95.4159, 29.7602, 0],
              [-95.4155, 29.7602, 0],
              [-95.4147, 29.7599, 0],
              [-95.4139, 29.7599, 0],
              [-95.4136, 29.76, 0],
              [-95.4133, 29.7604, 0],
              [-95.4132, 29.7617, 0],
              [-95.4131, 29.7621, 0],
              [-95.4128, 29.7623, 0],
              [-95.4117, 29.762, 0],
              [-95.4094, 29.7608, 0],
              [-95.4088, 29.7606, 0],
              [-95.408, 29.7606, 0],
              [-95.4068, 29.7609, 0],
              [-95.4044, 29.7609, 0],
              [-95.4032, 29.7612, 0],
              [-95.4026, 29.7614, 0],
              [-95.4023, 29.7617, 0],
              [-95.4015, 29.7619, 0],
              [-95.4003, 29.762, 0],
              [-95.3989, 29.7618, 0],
              [-95.3976, 29.7621, 0],
              [-95.3958, 29.7629, 0],
              [-95.3951, 29.763, 0],
              [-95.3932, 29.7626, 0],
              [-95.3915, 29.7626, 0],
              [-95.389, 29.7619, 0],
              [-95.3879, 29.7617, 0],
              [-95.3863, 29.7616, 0],
              [-95.3849, 29.7617, 0],
              [-95.3846, 29.7619, 0],
              [-95.3845, 29.7624, 0],
              [-95.384, 29.7633, 0],
              [-95.3834, 29.7637, 0],
              [-95.3829, 29.7638, 0],
              [-95.3825, 29.7637, 0],
              [-95.3821, 29.7633, 0],
              [-95.3815, 29.7623, 0],
              [-95.3812, 29.7622, 0],
              [-95.3805, 29.7621, 0],
              [-95.3799, 29.7623, 0],
              [-95.3789, 29.7623, 0],
              [-95.3785, 29.7622, 0],
              [-95.3779, 29.7618, 0],
              [-95.3773, 29.7613, 0],
              [-95.3767, 29.7612, 0],
              [-95.3763, 29.7611, 0],
              [-95.3752, 29.7613, 0],
              [-95.3745, 29.7614, 0],
              [-95.3736, 29.7612, 0],
              [-95.3728, 29.7613, 0],
              [-95.3721, 29.7617, 0],
              [-95.3715, 29.762, 0],
              [-95.3705, 29.7631, 0],
              [-95.3698, 29.7634, 0],
              [-95.3681, 29.7633, 0],
              [-95.3672, 29.7633, 0],
              [-95.3669, 29.7635, 0],
              [-95.3659, 29.7645, 0],
              [-95.3656, 29.7646, 0],
              [-95.3647, 29.7646, 0],
              [-95.3635, 29.7644, 0],
              [-95.363, 29.7644, 0],
              [-95.3617, 29.7649, 0],
              [-95.361, 29.765, 0],
              [-95.3595, 29.765, 0],
              [-95.3586, 29.7648, 0]
            ],
            [
              [-95.4742, 29.7723, 0],
              [-95.4732, 29.7722, 0],
              [-95.4728, 29.7719, 0],
              [-95.4723, 29.7707, 0],
              [-95.472, 29.7705, 0],
              [-95.4701, 29.7703, 0],
              [-95.4691, 29.7705, 0],
              [-95.4691, 29.7707, 0]
            ],
            [
              [-95.4691, 29.7707, 0],
              [-95.4683, 29.7707, 0],
              [-95.4681, 29.7701, 0],
              [-95.467, 29.7689, 0],
              [-95.4665, 29.7687, 0],
              [-95.466, 29.7686, 0],
              [-95.4655, 29.7688, 0],
              [-95.4651, 29.7689, 0],
              [-95.4649, 29.7688, 0],
              [-95.4649, 29.7682, 0],
              [-95.4651, 29.7671, 0],
              [-95.4649, 29.7669, 0],
              [-95.4644, 29.767, 0],
              [-95.4638, 29.7675, 0],
              [-95.4633, 29.7677, 0],
              [-95.4625, 29.7677, 0],
              [-95.4623, 29.7675, 0],
              [-95.462, 29.7664, 0],
              [-95.4619, 29.7662, 0],
              [-95.4611, 29.7659, 0],
              [-95.4605, 29.7654, 0],
              [-95.4603, 29.7653, 0],
              [-95.4591, 29.7652, 0],
              [-95.4582, 29.7645, 0],
              [-95.458, 29.7642, 0],
              [-95.458, 29.7638, 0],
              [-95.4582, 29.7633, 0],
              [-95.4587, 29.7629, 0],
              [-95.4593, 29.7628, 0],
              [-95.4605, 29.7629, 0],
              [-95.4607, 29.7628, 0],
              [-95.4607, 29.7625, 0],
              [-95.4605, 29.7624, 0],
              [-95.4596, 29.7622, 0],
              [-95.4595, 29.762, 0]
            ],
            [
              [-95.4595, 29.762, 0],
              [-95.4591, 29.762, 0],
              [-95.4582, 29.7617, 0],
              [-95.4579, 29.7615, 0],
              [-95.4579, 29.7608, 0],
              [-95.4581, 29.7604, 0],
              [-95.4581, 29.76, 0],
              [-95.4579, 29.7596, 0],
              [-95.4575, 29.7595, 0],
              [-95.4568, 29.7596, 0],
              [-95.456, 29.76, 0],
              [-95.4553, 29.76, 0],
              [-95.453, 29.7589, 0],
              [-95.4526, 29.7586, 0],
              [-95.4526, 29.7582, 0],
              [-95.4529, 29.7578, 0],
              [-95.4529, 29.7574, 0],
              [-95.4517, 29.7573, 0],
              [-95.4513, 29.7571, 0],
              [-95.4512, 29.7568, 0],
              [-95.4509, 29.7566, 0],
              [-95.4506, 29.7564, 0],
              [-95.4485, 29.7561, 0],
              [-95.447, 29.7556, 0],
              [-95.4466, 29.7553, 0],
              [-95.4464, 29.7549, 0],
              [-95.4464, 29.7544, 0],
              [-95.4462, 29.7541, 0],
              [-95.4457, 29.754, 0],
              [-95.4436, 29.7541, 0],
              [-95.4427, 29.7536, 0],
              [-95.4422, 29.7537, 0],
              [-95.4416, 29.7543, 0],
              [-95.4411, 29.7553, 0],
              [-95.4402, 29.756, 0],
              [-95.44, 29.7566, 0],
              [-95.4398, 29.7569, 0],
              [-95.439, 29.7571, 0],
              [-95.4386, 29.757, 0],
              [-95.4381, 29.757, 0],
              [-95.438, 29.7572, 0],
              [-95.438, 29.7575, 0],
              [-95.4382, 29.7578, 0],
              [-95.4391, 29.7586, 0],
              [-95.4392, 29.759, 0],
              [-95.4391, 29.7593, 0],
              [-95.4388, 29.7596, 0],
              [-95.4382, 29.7597, 0],
              [-95.438, 29.7596, 0],
              [-95.4362, 29.7584, 0],
              [-95.4356, 29.758, 0],
              [-95.4345, 29.7579, 0],
              [-95.4342, 29.7578, 0],
              [-95.4337, 29.7576, 0],
              [-95.4333, 29.7579, 0],
              [-95.4332, 29.7581, 0],
              [-95.4333, 29.7597, 0],
              [-95.433, 29.7599, 0],
              [-95.4323, 29.7599, 0],
              [-95.432, 29.7598, 0]
            ],
            [
              [-95.432, 29.7598, 0],
              [-95.431, 29.7588, 0],
              [-95.4303, 29.7585, 0],
              [-95.4293, 29.7583, 0],
              [-95.429, 29.7584, 0],
              [-95.4285, 29.7588, 0],
              [-95.4285, 29.7593, 0],
              [-95.4293, 29.7601, 0],
              [-95.4293, 29.7605, 0],
              [-95.4289, 29.7606, 0],
              [-95.4277, 29.7604, 0],
              [-95.4273, 29.7598, 0],
              [-95.4272, 29.7592, 0],
              [-95.4271, 29.759, 0],
              [-95.4271, 29.7589, 0],
              [-95.4268, 29.7585, 0],
              [-95.4262, 29.7584, 0],
              [-95.4259, 29.758, 0],
              [-95.4256, 29.7572, 0],
              [-95.4253, 29.7567, 0],
              [-95.4248, 29.7567, 0],
              [-95.4246, 29.7569, 0],
              [-95.4244, 29.7576, 0],
              [-95.424, 29.7584, 0],
              [-95.4235, 29.7584, 0],
              [-95.423, 29.7581, 0],
              [-95.4229, 29.7578, 0],
              [-95.4225, 29.7575, 0],
              [-95.422, 29.7576, 0],
              [-95.4218, 29.7577, 0],
              [-95.4212, 29.7582, 0],
              [-95.421, 29.7586, 0],
              [-95.4203, 29.7593, 0],
              [-95.42, 29.7593, 0],
              [-95.4193, 29.7587, 0],
              [-95.419, 29.7583, 0],
              [-95.419, 29.758, 0],
              [-95.4187, 29.7577, 0],
              [-95.4185, 29.7576, 0],
              [-95.4181, 29.7577, 0],
              [-95.4172, 29.7586, 0],
              [-95.4165, 29.7595, 0],
              [-95.4161, 29.7601, 0],
              [-95.4159, 29.7602, 0],
              [-95.4155, 29.7602, 0],
              [-95.4147, 29.7599, 0],
              [-95.4139, 29.7599, 0],
              [-95.4136, 29.76, 0],
              [-95.4133, 29.7604, 0],
              [-95.4132, 29.7617, 0],
              [-95.4131, 29.7621, 0],
              [-95.4128, 29.7623, 0],
              [-95.4117, 29.762, 0],
              [-95.4094, 29.7608, 0],
              [-95.4088, 29.7606, 0],
              [-95.408, 29.7606, 0],
              [-95.4068, 29.7609, 0],
              [-95.4044, 29.7609, 0],
              [-95.4032, 29.7612, 0],
              [-95.4026, 29.7614, 0],
              [-95.4023, 29.7617, 0],
              [-95.4015, 29.7619, 0],
              [-95.4003, 29.762, 0],
              [-95.3989, 29.7618, 0],
              [-95.3976, 29.7621, 0],
              [-95.3958, 29.7629, 0],
              [-95.3951, 29.763, 0],
              [-95.3932, 29.7626, 0],
              [-95.3915, 29.7626, 0],
              [-95.389, 29.7619, 0],
              [-95.3879, 29.7617, 0],
              [-95.3863, 29.7616, 0],
              [-95.3849, 29.7617, 0],
              [-95.3846, 29.7619, 0],
              [-95.3845, 29.7624, 0],
              [-95.384, 29.7633, 0],
              [-95.3834, 29.7637, 0],
              [-95.3829, 29.7638, 0],
              [-95.3825, 29.7637, 0],
              [-95.3821, 29.7633, 0],
              [-95.3815, 29.7623, 0],
              [-95.3812, 29.7622, 0],
              [-95.3805, 29.7621, 0],
              [-95.3799, 29.7623, 0],
              [-95.3789, 29.7623, 0],
              [-95.3785, 29.7622, 0],
              [-95.3779, 29.7618, 0],
              [-95.3773, 29.7613, 0],
              [-95.3767, 29.7612, 0],
              [-95.3763, 29.7611, 0],
              [-95.3752, 29.7613, 0],
              [-95.3745, 29.7614, 0],
              [-95.3736, 29.7612, 0],
              [-95.3728, 29.7613, 0],
              [-95.3721, 29.7617, 0],
              [-95.3715, 29.762, 0],
              [-95.3705, 29.7631, 0],
              [-95.3698, 29.7634, 0],
              [-95.3681, 29.7633, 0],
              [-95.3672, 29.7633, 0],
              [-95.3669, 29.7635, 0],
              [-95.3659, 29.7645, 0],
              [-95.3656, 29.7646, 0],
              [-95.3647, 29.7646, 0],
              [-95.3635, 29.7644, 0],
              [-95.363, 29.7644, 0],
              [-95.3617, 29.7649, 0],
              [-95.361, 29.765, 0],
              [-95.3595, 29.765, 0],
              [-95.3586, 29.7648, 0]
            ],
            [
              [-95.4791, 29.7733, 0],
              [-95.4786, 29.7732, 0],
              [-95.4779, 29.7728, 0],
              [-95.4771, 29.7721, 0],
              [-95.4767, 29.7715, 0],
              [-95.4761, 29.7711, 0],
              [-95.4759, 29.7712, 0],
              [-95.4754, 29.7716, 0],
              [-95.4751, 29.7722, 0],
              [-95.4749, 29.7723, 0],
              [-95.4742, 29.7723, 0]
            ],
            [
              [-95.4742, 29.7723, 0],
              [-95.4732, 29.7722, 0],
              [-95.4728, 29.7719, 0],
              [-95.4723, 29.7707, 0],
              [-95.472, 29.7705, 0],
              [-95.4701, 29.7703, 0],
              [-95.4691, 29.7705, 0],
              [-95.4691, 29.7707, 0]
            ],
            [
              [-95.4691, 29.7707, 0],
              [-95.4683, 29.7707, 0],
              [-95.4681, 29.7701, 0],
              [-95.467, 29.7689, 0],
              [-95.4665, 29.7687, 0],
              [-95.466, 29.7686, 0],
              [-95.4655, 29.7688, 0],
              [-95.4651, 29.7689, 0],
              [-95.4649, 29.7688, 0],
              [-95.4649, 29.7682, 0],
              [-95.4651, 29.7671, 0],
              [-95.4649, 29.7669, 0],
              [-95.4644, 29.767, 0],
              [-95.4638, 29.7675, 0],
              [-95.4633, 29.7677, 0],
              [-95.4625, 29.7677, 0],
              [-95.4623, 29.7675, 0],
              [-95.462, 29.7664, 0],
              [-95.4619, 29.7662, 0],
              [-95.4611, 29.7659, 0],
              [-95.4605, 29.7654, 0],
              [-95.4603, 29.7653, 0],
              [-95.4591, 29.7652, 0],
              [-95.4582, 29.7645, 0],
              [-95.458, 29.7642, 0],
              [-95.458, 29.7638, 0],
              [-95.4582, 29.7633, 0],
              [-95.4587, 29.7629, 0],
              [-95.4593, 29.7628, 0],
              [-95.4605, 29.7629, 0],
              [-95.4607, 29.7628, 0],
              [-95.4607, 29.7625, 0],
              [-95.4605, 29.7624, 0],
              [-95.4596, 29.7622, 0],
              [-95.4595, 29.762, 0]
            ],
            [
              [-95.4595, 29.762, 0],
              [-95.4591, 29.762, 0],
              [-95.4582, 29.7617, 0],
              [-95.4579, 29.7615, 0],
              [-95.4579, 29.7608, 0],
              [-95.4581, 29.7604, 0],
              [-95.4581, 29.76, 0],
              [-95.4579, 29.7596, 0],
              [-95.4575, 29.7595, 0],
              [-95.4568, 29.7596, 0],
              [-95.456, 29.76, 0],
              [-95.4553, 29.76, 0],
              [-95.453, 29.7589, 0],
              [-95.4526, 29.7586, 0],
              [-95.4526, 29.7582, 0],
              [-95.4529, 29.7578, 0],
              [-95.4529, 29.7574, 0],
              [-95.4517, 29.7573, 0],
              [-95.4513, 29.7571, 0],
              [-95.4512, 29.7568, 0],
              [-95.4509, 29.7566, 0],
              [-95.4506, 29.7564, 0],
              [-95.4485, 29.7561, 0],
              [-95.447, 29.7556, 0],
              [-95.4466, 29.7553, 0],
              [-95.4464, 29.7549, 0],
              [-95.4464, 29.7544, 0],
              [-95.4462, 29.7541, 0],
              [-95.4457, 29.754, 0],
              [-95.4436, 29.7541, 0],
              [-95.4427, 29.7536, 0],
              [-95.4422, 29.7537, 0],
              [-95.4416, 29.7543, 0],
              [-95.4411, 29.7553, 0],
              [-95.4402, 29.756, 0],
              [-95.44, 29.7566, 0],
              [-95.4398, 29.7569, 0],
              [-95.439, 29.7571, 0],
              [-95.4386, 29.757, 0],
              [-95.4381, 29.757, 0],
              [-95.438, 29.7572, 0],
              [-95.438, 29.7575, 0],
              [-95.4382, 29.7578, 0],
              [-95.4391, 29.7586, 0],
              [-95.4392, 29.759, 0],
              [-95.4391, 29.7593, 0],
              [-95.4388, 29.7596, 0],
              [-95.4382, 29.7597, 0],
              [-95.438, 29.7596, 0],
              [-95.4362, 29.7584, 0],
              [-95.4356, 29.758, 0],
              [-95.4345, 29.7579, 0],
              [-95.4342, 29.7578, 0],
              [-95.4337, 29.7576, 0],
              [-95.4333, 29.7579, 0],
              [-95.4332, 29.7581, 0],
              [-95.4333, 29.7597, 0],
              [-95.433, 29.7599, 0],
              [-95.4323, 29.7599, 0],
              [-95.432, 29.7598, 0]
            ],
            [
              [-95.432, 29.7598, 0],
              [-95.431, 29.7588, 0],
              [-95.4303, 29.7585, 0],
              [-95.4293, 29.7583, 0],
              [-95.429, 29.7584, 0],
              [-95.4285, 29.7588, 0],
              [-95.4285, 29.7593, 0],
              [-95.4293, 29.7601, 0],
              [-95.4293, 29.7605, 0],
              [-95.4289, 29.7606, 0],
              [-95.4277, 29.7604, 0],
              [-95.4273, 29.7598, 0],
              [-95.4272, 29.7592, 0],
              [-95.4271, 29.759, 0],
              [-95.4271, 29.7589, 0],
              [-95.4268, 29.7585, 0],
              [-95.4262, 29.7584, 0],
              [-95.4259, 29.758, 0],
              [-95.4256, 29.7572, 0],
              [-95.4253, 29.7567, 0],
              [-95.4248, 29.7567, 0],
              [-95.4246, 29.7569, 0],
              [-95.4244, 29.7576, 0],
              [-95.424, 29.7584, 0],
              [-95.4235, 29.7584, 0],
              [-95.423, 29.7581, 0],
              [-95.4229, 29.7578, 0],
              [-95.4225, 29.7575, 0],
              [-95.422, 29.7576, 0],
              [-95.4218, 29.7577, 0],
              [-95.4212, 29.7582, 0],
              [-95.421, 29.7586, 0],
              [-95.4203, 29.7593, 0],
              [-95.42, 29.7593, 0],
              [-95.4193, 29.7587, 0],
              [-95.419, 29.7583, 0],
              [-95.419, 29.758, 0],
              [-95.4187, 29.7577, 0],
              [-95.4185, 29.7576, 0],
              [-95.4181, 29.7577, 0],
              [-95.4172, 29.7586, 0],
              [-95.4165, 29.7595, 0],
              [-95.4161, 29.7601, 0],
              [-95.4159, 29.7602, 0],
              [-95.4155, 29.7602, 0],
              [-95.4147, 29.7599, 0],
              [-95.4139, 29.7599, 0],
              [-95.4136, 29.76, 0],
              [-95.4133, 29.7604, 0],
              [-95.4132, 29.7617, 0],
              [-95.4131, 29.7621, 0],
              [-95.4128, 29.7623, 0],
              [-95.4117, 29.762, 0],
              [-95.4094, 29.7608, 0],
              [-95.4088, 29.7606, 0],
              [-95.408, 29.7606, 0],
              [-95.4068, 29.7609, 0],
              [-95.4044, 29.7609, 0],
              [-95.4032, 29.7612, 0],
              [-95.4026, 29.7614, 0],
              [-95.4023, 29.7617, 0],
              [-95.4015, 29.7619, 0],
              [-95.4003, 29.762, 0],
              [-95.3989, 29.7618, 0],
              [-95.3976, 29.7621, 0],
              [-95.3958, 29.7629, 0],
              [-95.3951, 29.763, 0],
              [-95.3932, 29.7626, 0],
              [-95.3915, 29.7626, 0],
              [-95.389, 29.7619, 0],
              [-95.3879, 29.7617, 0],
              [-95.3863, 29.7616, 0],
              [-95.3849, 29.7617, 0],
              [-95.3846, 29.7619, 0],
              [-95.3845, 29.7624, 0],
              [-95.384, 29.7633, 0],
              [-95.3834, 29.7637, 0],
              [-95.3829, 29.7638, 0],
              [-95.3825, 29.7637, 0],
              [-95.3821, 29.7633, 0],
              [-95.3815, 29.7623, 0],
              [-95.3812, 29.7622, 0],
              [-95.3805, 29.7621, 0],
              [-95.3799, 29.7623, 0],
              [-95.3789, 29.7623, 0],
              [-95.3785, 29.7622, 0],
              [-95.3779, 29.7618, 0],
              [-95.3773, 29.7613, 0],
              [-95.3767, 29.7612, 0],
              [-95.3763, 29.7611, 0],
              [-95.3752, 29.7613, 0],
              [-95.3745, 29.7614, 0],
              [-95.3736, 29.7612, 0],
              [-95.3728, 29.7613, 0],
              [-95.3721, 29.7617, 0],
              [-95.3715, 29.762, 0],
              [-95.3705, 29.7631, 0],
              [-95.3698, 29.7634, 0],
              [-95.3681, 29.7633, 0],
              [-95.3672, 29.7633, 0],
              [-95.3669, 29.7635, 0],
              [-95.3659, 29.7645, 0],
              [-95.3656, 29.7646, 0],
              [-95.3647, 29.7646, 0],
              [-95.3635, 29.7644, 0],
              [-95.363, 29.7644, 0],
              [-95.3617, 29.7649, 0],
              [-95.361, 29.765, 0],
              [-95.3595, 29.765, 0],
              [-95.3586, 29.7648, 0]
            ],
            [
              [-95.496, 29.7627, 0],
              [-95.4959, 29.7632, 0],
              [-95.4956, 29.7635, 0],
              [-95.4951, 29.7638, 0],
              [-95.4949, 29.7641, 0],
              [-95.4949, 29.7646, 0],
              [-95.4947, 29.7649, 0],
              [-95.4942, 29.7651, 0],
              [-95.493, 29.765, 0],
              [-95.4926, 29.7647, 0],
              [-95.4923, 29.7643, 0],
              [-95.4923, 29.7632, 0],
              [-95.4921, 29.7631, 0],
              [-95.4915, 29.7631, 0],
              [-95.491, 29.7634, 0],
              [-95.4908, 29.7638, 0],
              [-95.4908, 29.764, 0],
              [-95.4909, 29.7642, 0],
              [-95.4922, 29.7651, 0],
              [-95.4922, 29.7654, 0],
              [-95.492, 29.7655, 0],
              [-95.4913, 29.7655, 0],
              [-95.4909, 29.7653, 0],
              [-95.4901, 29.7647, 0],
              [-95.4897, 29.7647, 0],
              [-95.4896, 29.765, 0],
              [-95.4896, 29.7653, 0],
              [-95.4899, 29.7657, 0],
              [-95.491, 29.7663, 0],
              [-95.491, 29.7666, 0],
              [-95.4908, 29.7666, 0],
              [-95.4898, 29.7666, 0],
              [-95.4888, 29.7666, 0],
              [-95.4881, 29.7669, 0],
              [-95.4878, 29.7672, 0],
              [-95.4874, 29.768, 0],
              [-95.4874, 29.7685, 0],
              [-95.4876, 29.7688, 0],
              [-95.4882, 29.7691, 0],
              [-95.4881, 29.7694, 0],
              [-95.4877, 29.7696, 0],
              [-95.4867, 29.7694, 0],
              [-95.4863, 29.7691, 0],
              [-95.4857, 29.7691, 0],
              [-95.4854, 29.7693, 0],
              [-95.4853, 29.7695, 0],
              [-95.4853, 29.7702, 0],
              [-95.485, 29.7708, 0],
              [-95.4844, 29.7713, 0],
              [-95.4835, 29.7716, 0],
              [-95.4832, 29.7719, 0],
              [-95.483, 29.7719, 0],
              [-95.4828, 29.7718, 0],
              [-95.4829, 29.771, 0],
              [-95.483, 29.7708, 0],
              [-95.4831, 29.7703, 0],
              [-95.4829, 29.7701, 0],
              [-95.4822, 29.7701, 0],
              [-95.4817, 29.7705, 0],
              [-95.4816, 29.7709, 0],
              [-95.4816, 29.7724, 0],
              [-95.4812, 29.7729, 0],
              [-95.4808, 29.7731, 0],
              [-95.4791, 29.7733, 0]
            ],
            [
              [-95.4791, 29.7733, 0],
              [-95.4786, 29.7732, 0],
              [-95.4779, 29.7728, 0],
              [-95.4771, 29.7721, 0],
              [-95.4767, 29.7715, 0],
              [-95.4761, 29.7711, 0],
              [-95.4759, 29.7712, 0],
              [-95.4754, 29.7716, 0],
              [-95.4751, 29.7722, 0],
              [-95.4749, 29.7723, 0],
              [-95.4742, 29.7723, 0]
            ],
            [
              [-95.4742, 29.7723, 0],
              [-95.4732, 29.7722, 0],
              [-95.4728, 29.7719, 0],
              [-95.4723, 29.7707, 0],
              [-95.472, 29.7705, 0],
              [-95.4701, 29.7703, 0],
              [-95.4691, 29.7705, 0],
              [-95.4691, 29.7707, 0]
            ],
            [
              [-95.4691, 29.7707, 0],
              [-95.4683, 29.7707, 0],
              [-95.4681, 29.7701, 0],
              [-95.467, 29.7689, 0],
              [-95.4665, 29.7687, 0],
              [-95.466, 29.7686, 0],
              [-95.4655, 29.7688, 0],
              [-95.4651, 29.7689, 0],
              [-95.4649, 29.7688, 0],
              [-95.4649, 29.7682, 0],
              [-95.4651, 29.7671, 0],
              [-95.4649, 29.7669, 0],
              [-95.4644, 29.767, 0],
              [-95.4638, 29.7675, 0],
              [-95.4633, 29.7677, 0],
              [-95.4625, 29.7677, 0],
              [-95.4623, 29.7675, 0],
              [-95.462, 29.7664, 0],
              [-95.4619, 29.7662, 0],
              [-95.4611, 29.7659, 0],
              [-95.4605, 29.7654, 0],
              [-95.4603, 29.7653, 0],
              [-95.4591, 29.7652, 0],
              [-95.4582, 29.7645, 0],
              [-95.458, 29.7642, 0],
              [-95.458, 29.7638, 0],
              [-95.4582, 29.7633, 0],
              [-95.4587, 29.7629, 0],
              [-95.4593, 29.7628, 0],
              [-95.4605, 29.7629, 0],
              [-95.4607, 29.7628, 0],
              [-95.4607, 29.7625, 0],
              [-95.4605, 29.7624, 0],
              [-95.4596, 29.7622, 0],
              [-95.4595, 29.762, 0]
            ],
            [
              [-95.4595, 29.762, 0],
              [-95.4591, 29.762, 0],
              [-95.4582, 29.7617, 0],
              [-95.4579, 29.7615, 0],
              [-95.4579, 29.7608, 0],
              [-95.4581, 29.7604, 0],
              [-95.4581, 29.76, 0],
              [-95.4579, 29.7596, 0],
              [-95.4575, 29.7595, 0],
              [-95.4568, 29.7596, 0],
              [-95.456, 29.76, 0],
              [-95.4553, 29.76, 0],
              [-95.453, 29.7589, 0],
              [-95.4526, 29.7586, 0],
              [-95.4526, 29.7582, 0],
              [-95.4529, 29.7578, 0],
              [-95.4529, 29.7574, 0],
              [-95.4517, 29.7573, 0],
              [-95.4513, 29.7571, 0],
              [-95.4512, 29.7568, 0],
              [-95.4509, 29.7566, 0],
              [-95.4506, 29.7564, 0],
              [-95.4485, 29.7561, 0],
              [-95.447, 29.7556, 0],
              [-95.4466, 29.7553, 0],
              [-95.4464, 29.7549, 0],
              [-95.4464, 29.7544, 0],
              [-95.4462, 29.7541, 0],
              [-95.4457, 29.754, 0],
              [-95.4436, 29.7541, 0],
              [-95.4427, 29.7536, 0],
              [-95.4422, 29.7537, 0],
              [-95.4416, 29.7543, 0],
              [-95.4411, 29.7553, 0],
              [-95.4402, 29.756, 0],
              [-95.44, 29.7566, 0],
              [-95.4398, 29.7569, 0],
              [-95.439, 29.7571, 0],
              [-95.4386, 29.757, 0],
              [-95.4381, 29.757, 0],
              [-95.438, 29.7572, 0],
              [-95.438, 29.7575, 0],
              [-95.4382, 29.7578, 0],
              [-95.4391, 29.7586, 0],
              [-95.4392, 29.759, 0],
              [-95.4391, 29.7593, 0],
              [-95.4388, 29.7596, 0],
              [-95.4382, 29.7597, 0],
              [-95.438, 29.7596, 0],
              [-95.4362, 29.7584, 0],
              [-95.4356, 29.758, 0],
              [-95.4345, 29.7579, 0],
              [-95.4342, 29.7578, 0],
              [-95.4337, 29.7576, 0],
              [-95.4333, 29.7579, 0],
              [-95.4332, 29.7581, 0],
              [-95.4333, 29.7597, 0],
              [-95.433, 29.7599, 0],
              [-95.4323, 29.7599, 0],
              [-95.432, 29.7598, 0]
            ],
            [
              [-95.432, 29.7598, 0],
              [-95.431, 29.7588, 0],
              [-95.4303, 29.7585, 0],
              [-95.4293, 29.7583, 0],
              [-95.429, 29.7584, 0],
              [-95.4285, 29.7588, 0],
              [-95.4285, 29.7593, 0],
              [-95.4293, 29.7601, 0],
              [-95.4293, 29.7605, 0],
              [-95.4289, 29.7606, 0],
              [-95.4277, 29.7604, 0],
              [-95.4273, 29.7598, 0],
              [-95.4272, 29.7592, 0],
              [-95.4271, 29.759, 0],
              [-95.4271, 29.7589, 0],
              [-95.4268, 29.7585, 0],
              [-95.4262, 29.7584, 0],
              [-95.4259, 29.758, 0],
              [-95.4256, 29.7572, 0],
              [-95.4253, 29.7567, 0],
              [-95.4248, 29.7567, 0],
              [-95.4246, 29.7569, 0],
              [-95.4244, 29.7576, 0],
              [-95.424, 29.7584, 0],
              [-95.4235, 29.7584, 0],
              [-95.423, 29.7581, 0],
              [-95.4229, 29.7578, 0],
              [-95.4225, 29.7575, 0],
              [-95.422, 29.7576, 0],
              [-95.4218, 29.7577, 0],
              [-95.4212, 29.7582, 0],
              [-95.421, 29.7586, 0],
              [-95.4203, 29.7593, 0],
              [-95.42, 29.7593, 0],
              [-95.4193, 29.7587, 0],
              [-95.419, 29.7583, 0],
              [-95.419, 29.758, 0],
              [-95.4187, 29.7577, 0],
              [-95.4185, 29.7576, 0],
              [-95.4181, 29.7577, 0],
              [-95.4172, 29.7586, 0],
              [-95.4165, 29.7595, 0],
              [-95.4161, 29.7601, 0],
              [-95.4159, 29.7602, 0],
              [-95.4155, 29.7602, 0],
              [-95.4147, 29.7599, 0],
              [-95.4139, 29.7599, 0],
              [-95.4136, 29.76, 0],
              [-95.4133, 29.7604, 0],
              [-95.4132, 29.7617, 0],
              [-95.4131, 29.7621, 0],
              [-95.4128, 29.7623, 0],
              [-95.4117, 29.762, 0],
              [-95.4094, 29.7608, 0],
              [-95.4088, 29.7606, 0],
              [-95.408, 29.7606, 0],
              [-95.4068, 29.7609, 0],
              [-95.4044, 29.7609, 0],
              [-95.4032, 29.7612, 0],
              [-95.4026, 29.7614, 0],
              [-95.4023, 29.7617, 0],
              [-95.4015, 29.7619, 0],
              [-95.4003, 29.762, 0],
              [-95.3989, 29.7618, 0],
              [-95.3976, 29.7621, 0],
              [-95.3958, 29.7629, 0],
              [-95.3951, 29.763, 0],
              [-95.3932, 29.7626, 0],
              [-95.3915, 29.7626, 0],
              [-95.389, 29.7619, 0],
              [-95.3879, 29.7617, 0],
              [-95.3863, 29.7616, 0],
              [-95.3849, 29.7617, 0],
              [-95.3846, 29.7619, 0],
              [-95.3845, 29.7624, 0],
              [-95.384, 29.7633, 0],
              [-95.3834, 29.7637, 0],
              [-95.3829, 29.7638, 0],
              [-95.3825, 29.7637, 0],
              [-95.3821, 29.7633, 0],
              [-95.3815, 29.7623, 0],
              [-95.3812, 29.7622, 0],
              [-95.3805, 29.7621, 0],
              [-95.3799, 29.7623, 0],
              [-95.3789, 29.7623, 0],
              [-95.3785, 29.7622, 0],
              [-95.3779, 29.7618, 0],
              [-95.3773, 29.7613, 0],
              [-95.3767, 29.7612, 0],
              [-95.3763, 29.7611, 0],
              [-95.3752, 29.7613, 0],
              [-95.3745, 29.7614, 0],
              [-95.3736, 29.7612, 0],
              [-95.3728, 29.7613, 0],
              [-95.3721, 29.7617, 0],
              [-95.3715, 29.762, 0],
              [-95.3705, 29.7631, 0],
              [-95.3698, 29.7634, 0],
              [-95.3681, 29.7633, 0],
              [-95.3672, 29.7633, 0],
              [-95.3669, 29.7635, 0],
              [-95.3659, 29.7645, 0],
              [-95.3656, 29.7646, 0],
              [-95.3647, 29.7646, 0],
              [-95.3635, 29.7644, 0],
              [-95.363, 29.7644, 0],
              [-95.3617, 29.7649, 0],
              [-95.361, 29.765, 0],
              [-95.3595, 29.765, 0],
              [-95.3586, 29.7648, 0]
            ],
            [
              [-95.507, 29.7465, 0],
              [-95.5079, 29.746, 0],
              [-95.5082, 29.746, 0],
              [-95.5086, 29.7462, 0],
              [-95.509, 29.7462, 0],
              [-95.5102, 29.7457, 0],
              [-95.5108, 29.7456, 0],
              [-95.5111, 29.7457, 0],
              [-95.5117, 29.7457, 0],
              [-95.5119, 29.7456, 0],
              [-95.5121, 29.7454, 0],
              [-95.5121, 29.745, 0],
              [-95.5119, 29.7443, 0],
              [-95.512, 29.7441, 0],
              [-95.5122, 29.7438, 0],
              [-95.5127, 29.7438, 0],
              [-95.513, 29.7439, 0],
              [-95.5137, 29.7446, 0],
              [-95.5142, 29.7449, 0],
              [-95.5147, 29.7449, 0],
              [-95.5156, 29.7441, 0],
              [-95.5158, 29.7437, 0],
              [-95.5162, 29.7434, 0],
              [-95.5168, 29.7434, 0],
              [-95.5171, 29.7437, 0],
              [-95.5173, 29.7437, 0],
              [-95.5175, 29.7436, 0],
              [-95.5178, 29.7429, 0],
              [-95.5179, 29.7428, 0],
              [-95.5185, 29.7428, 0],
              [-95.5187, 29.7429, 0],
              [-95.5189, 29.7435, 0],
              [-95.5197, 29.7443, 0],
              [-95.5196, 29.7447, 0],
              [-95.5192, 29.7447, 0],
              [-95.5193, 29.7452, 0],
              [-95.5196, 29.7454, 0],
              [-95.52, 29.7455, 0],
              [-95.5199, 29.7462, 0],
              [-95.5197, 29.7464, 0],
              [-95.5197, 29.7468, 0],
              [-95.5214, 29.7474, 0],
              [-95.522, 29.7478, 0],
              [-95.5224, 29.7482, 0],
              [-95.5227, 29.7482, 0],
              [-95.5228, 29.7473, 0],
              [-95.5228, 29.7472, 0],
              [-95.5235, 29.7468, 0],
              [-95.524, 29.7469, 0],
              [-95.5244, 29.7472, 0],
              [-95.5245, 29.7474, 0],
              [-95.5247, 29.7481, 0],
              [-95.5248, 29.7482, 0],
              [-95.5251, 29.7484, 0],
              [-95.5255, 29.7484, 0],
              [-95.5256, 29.7475, 0],
              [-95.526, 29.747, 0],
              [-95.5267, 29.7466, 0],
              [-95.5276, 29.7465, 0],
              [-95.5285, 29.746, 0],
              [-95.5286, 29.7458, 0]
            ],
            [
              [-95.5286, 29.7458, 0],
              [-95.5295, 29.7459, 0],
              [-95.5298, 29.7462, 0],
              [-95.5298, 29.7471, 0],
              [-95.5302, 29.7473, 0],
              [-95.5313, 29.7474, 0],
              [-95.5317, 29.7477, 0],
              [-95.532, 29.748, 0],
              [-95.532, 29.7485, 0],
              [-95.5319, 29.7487, 0],
              [-95.5311, 29.7493, 0],
              [-95.5309, 29.7495, 0],
              [-95.531, 29.7498, 0],
              [-95.5312, 29.7499, 0],
              [-95.5317, 29.75, 0],
              [-95.5326, 29.7498, 0],
              [-95.5334, 29.7495, 0],
              [-95.5341, 29.7496, 0],
              [-95.5344, 29.7498, 0],
              [-95.5348, 29.7502, 0],
              [-95.536, 29.7513, 0],
              [-95.5364, 29.7515, 0],
              [-95.5375, 29.7516, 0],
              [-95.5384, 29.7524, 0],
              [-95.5387, 29.7525, 0],
              [-95.5393, 29.7525, 0],
              [-95.5397, 29.7518, 0],
              [-95.54, 29.7517, 0],
              [-95.5406, 29.7518, 0],
              [-95.5414, 29.7517, 0],
              [-95.5419, 29.7519, 0],
              [-95.5419, 29.7526, 0],
              [-95.5422, 29.7529, 0],
              [-95.5426, 29.7531, 0],
              [-95.5429, 29.7532, 0],
              [-95.5455, 29.7531, 0],
              [-95.5457, 29.7532, 0],
              [-95.5457, 29.7536, 0],
              [-95.5452, 29.7541, 0],
              [-95.545, 29.7545, 0],
              [-95.5451, 29.7551, 0],
              [-95.5452, 29.7553, 0],
              [-95.5466, 29.7566, 0],
              [-95.5471, 29.7568, 0],
              [-95.548, 29.7572, 0],
              [-95.5483, 29.7574, 0],
              [-95.5483, 29.7578, 0],
              [-95.5477, 29.7587, 0],
              [-95.5478, 29.759, 0],
              [-95.5479, 29.7591, 0],
              [-95.5492, 29.7592, 0],
              [-95.5498, 29.7598, 0],
              [-95.5498, 29.7599, 0],
              [-95.5505, 29.7606, 0],
              [-95.5513, 29.7609, 0],
              [-95.5522, 29.7609, 0],
              [-95.5525, 29.7607, 0],
              [-95.5525, 29.7606, 0],
              [-95.5524, 29.7602, 0],
              [-95.5524, 29.7598, 0],
              [-95.5527, 29.7596, 0],
              [-95.554, 29.7593, 0],
              [-95.5544, 29.7594, 0],
              [-95.5545, 29.7598, 0],
              [-95.5543, 29.7603, 0],
              [-95.5544, 29.7608, 0],
              [-95.5547, 29.7611, 0],
              [-95.5553, 29.7613, 0],
              [-95.5556, 29.7616, 0],
              [-95.5558, 29.7621, 0],
              [-95.5561, 29.7625, 0],
              [-95.5567, 29.7626, 0],
              [-95.5581, 29.7624, 0]
            ],
            [
              [-95.5285, 29.746, 0],
              [-95.5286, 29.7458, 0]
            ],
            [
              [-95.5286, 29.7458, 0],
              [-95.5295, 29.7459, 0],
              [-95.5298, 29.7462, 0],
              [-95.5298, 29.7471, 0],
              [-95.5302, 29.7473, 0],
              [-95.5313, 29.7474, 0],
              [-95.5317, 29.7477, 0],
              [-95.532, 29.748, 0],
              [-95.532, 29.7485, 0],
              [-95.5319, 29.7487, 0],
              [-95.5311, 29.7493, 0],
              [-95.5309, 29.7495, 0],
              [-95.531, 29.7498, 0],
              [-95.5312, 29.7499, 0],
              [-95.5317, 29.75, 0],
              [-95.5326, 29.7498, 0],
              [-95.5334, 29.7495, 0],
              [-95.5341, 29.7496, 0],
              [-95.5344, 29.7498, 0],
              [-95.5348, 29.7502, 0],
              [-95.536, 29.7513, 0],
              [-95.5364, 29.7515, 0],
              [-95.5375, 29.7516, 0],
              [-95.5384, 29.7524, 0],
              [-95.5387, 29.7525, 0],
              [-95.5393, 29.7525, 0],
              [-95.5397, 29.7518, 0],
              [-95.54, 29.7517, 0],
              [-95.5406, 29.7518, 0],
              [-95.5414, 29.7517, 0],
              [-95.5419, 29.7519, 0],
              [-95.5419, 29.7526, 0],
              [-95.5422, 29.7529, 0],
              [-95.5426, 29.7531, 0],
              [-95.5429, 29.7532, 0],
              [-95.5455, 29.7531, 0],
              [-95.5457, 29.7532, 0],
              [-95.5457, 29.7536, 0],
              [-95.5452, 29.7541, 0],
              [-95.545, 29.7545, 0],
              [-95.5451, 29.7551, 0],
              [-95.5452, 29.7553, 0],
              [-95.5466, 29.7566, 0],
              [-95.5471, 29.7568, 0],
              [-95.548, 29.7572, 0],
              [-95.5483, 29.7574, 0],
              [-95.5483, 29.7578, 0],
              [-95.5477, 29.7587, 0],
              [-95.5478, 29.759, 0],
              [-95.5479, 29.7591, 0],
              [-95.5492, 29.7592, 0],
              [-95.5498, 29.7598, 0],
              [-95.5498, 29.7599, 0],
              [-95.5505, 29.7606, 0],
              [-95.5513, 29.7609, 0],
              [-95.5522, 29.7609, 0],
              [-95.5525, 29.7607, 0],
              [-95.5525, 29.7606, 0],
              [-95.5524, 29.7602, 0],
              [-95.5524, 29.7598, 0],
              [-95.5527, 29.7596, 0],
              [-95.554, 29.7593, 0],
              [-95.5544, 29.7594, 0],
              [-95.5545, 29.7598, 0],
              [-95.5543, 29.7603, 0],
              [-95.5544, 29.7608, 0],
              [-95.5547, 29.7611, 0],
              [-95.5553, 29.7613, 0],
              [-95.5556, 29.7616, 0],
              [-95.5558, 29.7621, 0],
              [-95.5561, 29.7625, 0],
              [-95.5567, 29.7626, 0],
              [-95.5581, 29.7624, 0]
            ],
            [
              [-95.4966, 29.7618, 0],
              [-95.4966, 29.7617, 0],
              [-95.4968, 29.7616, 0],
              [-95.4974, 29.7616, 0],
              [-95.4981, 29.7619, 0],
              [-95.4987, 29.7619, 0],
              [-95.4988, 29.7617, 0],
              [-95.4989, 29.7611, 0],
              [-95.4991, 29.7608, 0],
              [-95.4993, 29.7604, 0],
              [-95.4998, 29.7602, 0],
              [-95.5002, 29.7602, 0],
              [-95.5011, 29.7603, 0],
              [-95.5021, 29.76, 0],
              [-95.5025, 29.7596, 0],
              [-95.5027, 29.7591, 0],
              [-95.5027, 29.7586, 0],
              [-95.5026, 29.758, 0],
              [-95.5027, 29.7576, 0],
              [-95.503, 29.7575, 0],
              [-95.5034, 29.7574, 0],
              [-95.5041, 29.7578, 0],
              [-95.5049, 29.758, 0],
              [-95.5051, 29.7579, 0],
              [-95.5051, 29.7576, 0],
              [-95.505, 29.7574, 0],
              [-95.5045, 29.7572, 0],
              [-95.5044, 29.7571, 0],
              [-95.5044, 29.7568, 0],
              [-95.5058, 29.7568, 0],
              [-95.5065, 29.7563, 0],
              [-95.5067, 29.7558, 0],
              [-95.5067, 29.7553, 0],
              [-95.5064, 29.7548, 0],
              [-95.5061, 29.7546, 0],
              [-95.5046, 29.7541, 0],
              [-95.5043, 29.7536, 0],
              [-95.505, 29.7524, 0],
              [-95.5054, 29.7502, 0],
              [-95.5059, 29.7487, 0],
              [-95.5062, 29.7484, 0],
              [-95.5066, 29.7484, 0],
              [-95.5077, 29.7488, 0],
              [-95.5082, 29.7485, 0],
              [-95.5082, 29.7482, 0],
              [-95.508, 29.748, 0],
              [-95.5068, 29.7476, 0],
              [-95.5065, 29.7473, 0],
              [-95.5065, 29.7471, 0],
              [-95.507, 29.7465, 0],
              [-95.5079, 29.746, 0],
              [-95.5082, 29.746, 0],
              [-95.5086, 29.7462, 0],
              [-95.509, 29.7462, 0],
              [-95.5102, 29.7457, 0],
              [-95.5108, 29.7456, 0],
              [-95.5111, 29.7457, 0],
              [-95.5117, 29.7457, 0],
              [-95.5119, 29.7456, 0],
              [-95.5121, 29.7454, 0],
              [-95.5121, 29.745, 0],
              [-95.5119, 29.7443, 0],
              [-95.512, 29.7441, 0],
              [-95.5122, 29.7438, 0],
              [-95.5127, 29.7438, 0],
              [-95.513, 29.7439, 0],
              [-95.5137, 29.7446, 0],
              [-95.5142, 29.7449, 0],
              [-95.5147, 29.7449, 0],
              [-95.5156, 29.7441, 0],
              [-95.5158, 29.7437, 0],
              [-95.5162, 29.7434, 0],
              [-95.5168, 29.7434, 0],
              [-95.5171, 29.7437, 0],
              [-95.5173, 29.7437, 0],
              [-95.5175, 29.7436, 0],
              [-95.5178, 29.7429, 0],
              [-95.5179, 29.7428, 0],
              [-95.5185, 29.7428, 0],
              [-95.5187, 29.7429, 0],
              [-95.5189, 29.7435, 0],
              [-95.5197, 29.7443, 0],
              [-95.5196, 29.7447, 0],
              [-95.5192, 29.7447, 0],
              [-95.5193, 29.7452, 0],
              [-95.5196, 29.7454, 0],
              [-95.52, 29.7455, 0],
              [-95.5199, 29.7462, 0],
              [-95.5197, 29.7464, 0],
              [-95.5197, 29.7468, 0],
              [-95.5214, 29.7474, 0],
              [-95.522, 29.7478, 0],
              [-95.5224, 29.7482, 0],
              [-95.5227, 29.7482, 0],
              [-95.5228, 29.7473, 0],
              [-95.5228, 29.7472, 0],
              [-95.5235, 29.7468, 0],
              [-95.524, 29.7469, 0],
              [-95.5244, 29.7472, 0],
              [-95.5245, 29.7474, 0],
              [-95.5247, 29.7481, 0],
              [-95.5248, 29.7482, 0],
              [-95.5251, 29.7484, 0],
              [-95.5255, 29.7484, 0],
              [-95.5256, 29.7475, 0],
              [-95.526, 29.747, 0],
              [-95.5267, 29.7466, 0],
              [-95.5276, 29.7465, 0],
              [-95.5285, 29.746, 0],
              [-95.5286, 29.7458, 0]
            ],
            [
              [-95.5286, 29.7458, 0],
              [-95.5295, 29.7459, 0],
              [-95.5298, 29.7462, 0],
              [-95.5298, 29.7471, 0],
              [-95.5302, 29.7473, 0],
              [-95.5313, 29.7474, 0],
              [-95.5317, 29.7477, 0],
              [-95.532, 29.748, 0],
              [-95.532, 29.7485, 0],
              [-95.5319, 29.7487, 0],
              [-95.5311, 29.7493, 0],
              [-95.5309, 29.7495, 0],
              [-95.531, 29.7498, 0],
              [-95.5312, 29.7499, 0],
              [-95.5317, 29.75, 0],
              [-95.5326, 29.7498, 0],
              [-95.5334, 29.7495, 0],
              [-95.5341, 29.7496, 0],
              [-95.5344, 29.7498, 0],
              [-95.5348, 29.7502, 0],
              [-95.536, 29.7513, 0],
              [-95.5364, 29.7515, 0],
              [-95.5375, 29.7516, 0],
              [-95.5384, 29.7524, 0],
              [-95.5387, 29.7525, 0],
              [-95.5393, 29.7525, 0],
              [-95.5397, 29.7518, 0],
              [-95.54, 29.7517, 0],
              [-95.5406, 29.7518, 0],
              [-95.5414, 29.7517, 0],
              [-95.5419, 29.7519, 0],
              [-95.5419, 29.7526, 0],
              [-95.5422, 29.7529, 0],
              [-95.5426, 29.7531, 0],
              [-95.5429, 29.7532, 0],
              [-95.5455, 29.7531, 0],
              [-95.5457, 29.7532, 0],
              [-95.5457, 29.7536, 0],
              [-95.5452, 29.7541, 0],
              [-95.545, 29.7545, 0],
              [-95.5451, 29.7551, 0],
              [-95.5452, 29.7553, 0],
              [-95.5466, 29.7566, 0],
              [-95.5471, 29.7568, 0],
              [-95.548, 29.7572, 0],
              [-95.5483, 29.7574, 0],
              [-95.5483, 29.7578, 0],
              [-95.5477, 29.7587, 0],
              [-95.5478, 29.759, 0],
              [-95.5479, 29.7591, 0],
              [-95.5492, 29.7592, 0],
              [-95.5498, 29.7598, 0],
              [-95.5498, 29.7599, 0],
              [-95.5505, 29.7606, 0],
              [-95.5513, 29.7609, 0],
              [-95.5522, 29.7609, 0],
              [-95.5525, 29.7607, 0],
              [-95.5525, 29.7606, 0],
              [-95.5524, 29.7602, 0],
              [-95.5524, 29.7598, 0],
              [-95.5527, 29.7596, 0],
              [-95.554, 29.7593, 0],
              [-95.5544, 29.7594, 0],
              [-95.5545, 29.7598, 0],
              [-95.5543, 29.7603, 0],
              [-95.5544, 29.7608, 0],
              [-95.5547, 29.7611, 0],
              [-95.5553, 29.7613, 0],
              [-95.5556, 29.7616, 0],
              [-95.5558, 29.7621, 0],
              [-95.5561, 29.7625, 0],
              [-95.5567, 29.7626, 0],
              [-95.5581, 29.7624, 0]
            ],
            [
              [-95.5567, 29.7626, 0],
              [-95.5581, 29.7624, 0]
            ],
            [
              [-95.5387, 29.7525, 0],
              [-95.5393, 29.7525, 0],
              [-95.5397, 29.7518, 0],
              [-95.54, 29.7517, 0],
              [-95.5406, 29.7518, 0],
              [-95.5414, 29.7517, 0],
              [-95.5419, 29.7519, 0],
              [-95.5419, 29.7526, 0],
              [-95.5422, 29.7529, 0],
              [-95.5426, 29.7531, 0],
              [-95.5429, 29.7532, 0],
              [-95.5455, 29.7531, 0],
              [-95.5457, 29.7532, 0],
              [-95.5457, 29.7536, 0],
              [-95.5452, 29.7541, 0],
              [-95.545, 29.7545, 0],
              [-95.5451, 29.7551, 0],
              [-95.5452, 29.7553, 0],
              [-95.5466, 29.7566, 0],
              [-95.5471, 29.7568, 0],
              [-95.548, 29.7572, 0],
              [-95.5483, 29.7574, 0],
              [-95.5483, 29.7578, 0],
              [-95.5477, 29.7587, 0],
              [-95.5478, 29.759, 0],
              [-95.5479, 29.7591, 0],
              [-95.5492, 29.7592, 0],
              [-95.5498, 29.7598, 0],
              [-95.5498, 29.7599, 0],
              [-95.5505, 29.7606, 0],
              [-95.5513, 29.7609, 0],
              [-95.5522, 29.7609, 0],
              [-95.5525, 29.7607, 0],
              [-95.5525, 29.7606, 0],
              [-95.5524, 29.7602, 0],
              [-95.5524, 29.7598, 0],
              [-95.5527, 29.7596, 0],
              [-95.554, 29.7593, 0],
              [-95.5544, 29.7594, 0],
              [-95.5545, 29.7598, 0],
              [-95.5543, 29.7603, 0],
              [-95.5544, 29.7608, 0],
              [-95.5547, 29.7611, 0],
              [-95.5553, 29.7613, 0],
              [-95.5556, 29.7616, 0],
              [-95.5558, 29.7621, 0],
              [-95.5561, 29.7625, 0],
              [-95.5567, 29.7626, 0],
              [-95.5581, 29.7624, 0]
            ],
            [
              [-95.5626, 29.762, 0],
              [-95.5606, 29.7616, 0],
              [-95.5601, 29.7612, 0],
              [-95.5598, 29.7608, 0],
              [-95.5593, 29.7607, 0],
              [-95.5591, 29.7608, 0],
              [-95.5588, 29.7612, 0],
              [-95.5586, 29.7619, 0],
              [-95.5584, 29.762, 0]
            ],
            [
              [-95.6201, 29.7708, 0],
              [-95.62, 29.7707, 0],
              [-95.619, 29.7702, 0],
              [-95.6185, 29.7697, 0],
              [-95.6183, 29.7695, 0],
              [-95.6183, 29.7687, 0],
              [-95.6188, 29.7659, 0],
              [-95.619, 29.7645, 0],
              [-95.6187, 29.7641, 0],
              [-95.6182, 29.7636, 0],
              [-95.6124, 29.7608, 0],
              [-95.6119, 29.7606, 0],
              [-95.6114, 29.7607, 0],
              [-95.6074, 29.7618, 0],
              [-95.6066, 29.7619, 0],
              [-95.6021, 29.7619, 0],
              [-95.5948, 29.7594, 0],
              [-95.5937, 29.7592, 0],
              [-95.5911, 29.7593, 0],
              [-95.5903, 29.7595, 0],
              [-95.5898, 29.7597, 0],
              [-95.5887, 29.7603, 0],
              [-95.588, 29.761, 0],
              [-95.5871, 29.7626, 0],
              [-95.5864, 29.7641, 0],
              [-95.5861, 29.7647, 0],
              [-95.5857, 29.7652, 0],
              [-95.5852, 29.7655, 0],
              [-95.5841, 29.7658, 0],
              [-95.5831, 29.7659, 0],
              [-95.5811, 29.7659, 0],
              [-95.5802, 29.7661, 0],
              [-95.5796, 29.7665, 0],
              [-95.5793, 29.7668, 0],
              [-95.5786, 29.767, 0],
              [-95.5779, 29.767, 0],
              [-95.5772, 29.7668, 0],
              [-95.5765, 29.7662, 0],
              [-95.5729, 29.7639, 0],
              [-95.5717, 29.763, 0],
              [-95.5707, 29.7625, 0],
              [-95.5693, 29.7622, 0],
              [-95.5683, 29.762, 0],
              [-95.5635, 29.7621, 0],
              [-95.5626, 29.762, 0],
              [-95.5606, 29.7616, 0],
              [-95.5601, 29.7612, 0],
              [-95.5598, 29.7608, 0],
              [-95.5593, 29.7607, 0],
              [-95.5591, 29.7608, 0],
              [-95.5588, 29.7612, 0],
              [-95.5586, 29.7619, 0],
              [-95.5584, 29.762, 0]
            ],
            [
              [-95.6232, 29.7727, 0],
              [-95.6224, 29.7721, 0],
              [-95.6201, 29.7708, 0]
            ],
            [
              [-95.6201, 29.7708, 0],
              [-95.62, 29.7707, 0],
              [-95.619, 29.7702, 0],
              [-95.6185, 29.7697, 0],
              [-95.6183, 29.7695, 0],
              [-95.6183, 29.7687, 0],
              [-95.6188, 29.7659, 0],
              [-95.619, 29.7645, 0],
              [-95.6187, 29.7641, 0],
              [-95.6182, 29.7636, 0],
              [-95.6124, 29.7608, 0],
              [-95.6119, 29.7606, 0],
              [-95.6114, 29.7607, 0],
              [-95.6074, 29.7618, 0],
              [-95.6066, 29.7619, 0],
              [-95.6021, 29.7619, 0],
              [-95.5948, 29.7594, 0],
              [-95.5937, 29.7592, 0],
              [-95.5911, 29.7593, 0],
              [-95.5903, 29.7595, 0],
              [-95.5898, 29.7597, 0],
              [-95.5887, 29.7603, 0],
              [-95.588, 29.761, 0],
              [-95.5871, 29.7626, 0],
              [-95.5864, 29.7641, 0],
              [-95.5861, 29.7647, 0],
              [-95.5857, 29.7652, 0],
              [-95.5852, 29.7655, 0],
              [-95.5841, 29.7658, 0],
              [-95.5831, 29.7659, 0],
              [-95.5811, 29.7659, 0],
              [-95.5802, 29.7661, 0],
              [-95.5796, 29.7665, 0],
              [-95.5793, 29.7668, 0],
              [-95.5786, 29.767, 0],
              [-95.5779, 29.767, 0],
              [-95.5772, 29.7668, 0],
              [-95.5765, 29.7662, 0],
              [-95.5729, 29.7639, 0],
              [-95.5717, 29.763, 0],
              [-95.5707, 29.7625, 0],
              [-95.5693, 29.7622, 0],
              [-95.5683, 29.762, 0],
              [-95.5635, 29.7621, 0],
              [-95.5626, 29.762, 0],
              [-95.5606, 29.7616, 0],
              [-95.5601, 29.7612, 0],
              [-95.5598, 29.7608, 0],
              [-95.5593, 29.7607, 0],
              [-95.5591, 29.7608, 0],
              [-95.5588, 29.7612, 0],
              [-95.5586, 29.7619, 0],
              [-95.5584, 29.762, 0]
            ],
            [
              [-95.6439, 29.7695, 0],
              [-95.6408, 29.7688, 0],
              [-95.6396, 29.769, 0],
              [-95.6361, 29.77, 0],
              [-95.6346, 29.7705, 0],
              [-95.6339, 29.7713, 0],
              [-95.6337, 29.7718, 0],
              [-95.6335, 29.7729, 0],
              [-95.633, 29.7736, 0],
              [-95.6321, 29.7739, 0],
              [-95.6252, 29.7736, 0],
              [-95.6248, 29.7735, 0],
              [-95.6235, 29.7728, 0],
              [-95.6232, 29.7727, 0]
            ],
            [
              [-95.6232, 29.7727, 0],
              [-95.6224, 29.7721, 0],
              [-95.6201, 29.7708, 0]
            ],
            [
              [-95.6201, 29.7708, 0],
              [-95.62, 29.7707, 0],
              [-95.619, 29.7702, 0],
              [-95.6185, 29.7697, 0],
              [-95.6183, 29.7695, 0],
              [-95.6183, 29.7687, 0],
              [-95.6188, 29.7659, 0],
              [-95.619, 29.7645, 0],
              [-95.6187, 29.7641, 0],
              [-95.6182, 29.7636, 0],
              [-95.6124, 29.7608, 0],
              [-95.6119, 29.7606, 0],
              [-95.6114, 29.7607, 0],
              [-95.6074, 29.7618, 0],
              [-95.6066, 29.7619, 0],
              [-95.6021, 29.7619, 0],
              [-95.5948, 29.7594, 0],
              [-95.5937, 29.7592, 0],
              [-95.5911, 29.7593, 0],
              [-95.5903, 29.7595, 0],
              [-95.5898, 29.7597, 0],
              [-95.5887, 29.7603, 0],
              [-95.588, 29.761, 0],
              [-95.5871, 29.7626, 0],
              [-95.5864, 29.7641, 0],
              [-95.5861, 29.7647, 0],
              [-95.5857, 29.7652, 0],
              [-95.5852, 29.7655, 0],
              [-95.5841, 29.7658, 0],
              [-95.5831, 29.7659, 0],
              [-95.5811, 29.7659, 0],
              [-95.5802, 29.7661, 0],
              [-95.5796, 29.7665, 0],
              [-95.5793, 29.7668, 0],
              [-95.5786, 29.767, 0],
              [-95.5779, 29.767, 0],
              [-95.5772, 29.7668, 0],
              [-95.5765, 29.7662, 0],
              [-95.5729, 29.7639, 0],
              [-95.5717, 29.763, 0],
              [-95.5707, 29.7625, 0],
              [-95.5693, 29.7622, 0],
              [-95.5683, 29.762, 0],
              [-95.5635, 29.7621, 0],
              [-95.5626, 29.762, 0],
              [-95.5606, 29.7616, 0],
              [-95.5601, 29.7612, 0],
              [-95.5598, 29.7608, 0],
              [-95.5593, 29.7607, 0],
              [-95.5591, 29.7608, 0],
              [-95.5588, 29.7612, 0],
              [-95.5586, 29.7619, 0],
              [-95.5584, 29.762, 0]
            ],
            [
              [-95.6468, 29.7696, 0],
              [-95.6466, 29.7696, 0],
              [-95.6439, 29.7695, 0],
              [-95.6408, 29.7688, 0],
              [-95.6396, 29.769, 0],
              [-95.6361, 29.77, 0],
              [-95.6346, 29.7705, 0],
              [-95.6339, 29.7713, 0],
              [-95.6337, 29.7718, 0],
              [-95.6335, 29.7729, 0],
              [-95.633, 29.7736, 0],
              [-95.6321, 29.7739, 0],
              [-95.6252, 29.7736, 0],
              [-95.6248, 29.7735, 0],
              [-95.6235, 29.7728, 0],
              [-95.6232, 29.7727, 0]
            ],
            [
              [-95.6232, 29.7727, 0],
              [-95.6224, 29.7721, 0],
              [-95.6201, 29.7708, 0]
            ],
            [
              [-95.6201, 29.7708, 0],
              [-95.62, 29.7707, 0],
              [-95.619, 29.7702, 0],
              [-95.6185, 29.7697, 0],
              [-95.6183, 29.7695, 0],
              [-95.6183, 29.7687, 0],
              [-95.6188, 29.7659, 0],
              [-95.619, 29.7645, 0],
              [-95.6187, 29.7641, 0],
              [-95.6182, 29.7636, 0],
              [-95.6124, 29.7608, 0],
              [-95.6119, 29.7606, 0],
              [-95.6114, 29.7607, 0],
              [-95.6074, 29.7618, 0],
              [-95.6066, 29.7619, 0],
              [-95.6021, 29.7619, 0],
              [-95.5948, 29.7594, 0],
              [-95.5937, 29.7592, 0],
              [-95.5911, 29.7593, 0],
              [-95.5903, 29.7595, 0],
              [-95.5898, 29.7597, 0],
              [-95.5887, 29.7603, 0],
              [-95.588, 29.761, 0],
              [-95.5871, 29.7626, 0],
              [-95.5864, 29.7641, 0],
              [-95.5861, 29.7647, 0],
              [-95.5857, 29.7652, 0],
              [-95.5852, 29.7655, 0],
              [-95.5841, 29.7658, 0],
              [-95.5831, 29.7659, 0],
              [-95.5811, 29.7659, 0],
              [-95.5802, 29.7661, 0],
              [-95.5796, 29.7665, 0],
              [-95.5793, 29.7668, 0],
              [-95.5786, 29.767, 0],
              [-95.5779, 29.767, 0],
              [-95.5772, 29.7668, 0],
              [-95.5765, 29.7662, 0],
              [-95.5729, 29.7639, 0],
              [-95.5717, 29.763, 0],
              [-95.5707, 29.7625, 0],
              [-95.5693, 29.7622, 0],
              [-95.5683, 29.762, 0],
              [-95.5635, 29.7621, 0],
              [-95.5626, 29.762, 0],
              [-95.5606, 29.7616, 0],
              [-95.5601, 29.7612, 0],
              [-95.5598, 29.7608, 0],
              [-95.5593, 29.7607, 0],
              [-95.5591, 29.7608, 0],
              [-95.5588, 29.7612, 0],
              [-95.5586, 29.7619, 0],
              [-95.5584, 29.762, 0]
            ],
            [
              [-95.6468, 29.7696, 0],
              [-95.6466, 29.7696, 0],
              [-95.6439, 29.7695, 0],
              [-95.6408, 29.7688, 0],
              [-95.6396, 29.769, 0],
              [-95.6361, 29.77, 0],
              [-95.6346, 29.7705, 0],
              [-95.6339, 29.7713, 0],
              [-95.6337, 29.7718, 0],
              [-95.6335, 29.7729, 0],
              [-95.633, 29.7736, 0],
              [-95.6321, 29.7739, 0],
              [-95.6252, 29.7736, 0],
              [-95.6248, 29.7735, 0],
              [-95.6235, 29.7728, 0],
              [-95.6232, 29.7727, 0]
            ],
            [
              [-95.6232, 29.7727, 0],
              [-95.6224, 29.7721, 0],
              [-95.6201, 29.7708, 0]
            ],
            [
              [-95.6201, 29.7708, 0],
              [-95.62, 29.7707, 0],
              [-95.619, 29.7702, 0],
              [-95.6185, 29.7697, 0],
              [-95.6183, 29.7695, 0],
              [-95.6183, 29.7687, 0],
              [-95.6188, 29.7659, 0],
              [-95.619, 29.7645, 0],
              [-95.6187, 29.7641, 0],
              [-95.6182, 29.7636, 0],
              [-95.6124, 29.7608, 0],
              [-95.6119, 29.7606, 0],
              [-95.6114, 29.7607, 0],
              [-95.6074, 29.7618, 0],
              [-95.6066, 29.7619, 0],
              [-95.6021, 29.7619, 0],
              [-95.5948, 29.7594, 0],
              [-95.5937, 29.7592, 0],
              [-95.5911, 29.7593, 0],
              [-95.5903, 29.7595, 0],
              [-95.5898, 29.7597, 0],
              [-95.5887, 29.7603, 0],
              [-95.588, 29.761, 0],
              [-95.5871, 29.7626, 0],
              [-95.5864, 29.7641, 0],
              [-95.5861, 29.7647, 0],
              [-95.5857, 29.7652, 0],
              [-95.5852, 29.7655, 0],
              [-95.5841, 29.7658, 0],
              [-95.5831, 29.7659, 0],
              [-95.5811, 29.7659, 0],
              [-95.5802, 29.7661, 0],
              [-95.5796, 29.7665, 0],
              [-95.5793, 29.7668, 0],
              [-95.5786, 29.767, 0],
              [-95.5779, 29.767, 0],
              [-95.5772, 29.7668, 0],
              [-95.5765, 29.7662, 0],
              [-95.5729, 29.7639, 0],
              [-95.5717, 29.763, 0],
              [-95.5707, 29.7625, 0],
              [-95.5693, 29.7622, 0],
              [-95.5683, 29.762, 0],
              [-95.5635, 29.7621, 0],
              [-95.5626, 29.762, 0],
              [-95.5606, 29.7616, 0],
              [-95.5601, 29.7612, 0],
              [-95.5598, 29.7608, 0],
              [-95.5593, 29.7607, 0],
              [-95.5591, 29.7608, 0],
              [-95.5588, 29.7612, 0],
              [-95.5586, 29.7619, 0],
              [-95.5584, 29.762, 0]
            ],
            [
              [-95.6468, 29.7696, 0],
              [-95.6466, 29.7696, 0],
              [-95.6439, 29.7695, 0],
              [-95.6408, 29.7688, 0],
              [-95.6396, 29.769, 0],
              [-95.6361, 29.77, 0],
              [-95.6346, 29.7705, 0],
              [-95.6339, 29.7713, 0],
              [-95.6337, 29.7718, 0],
              [-95.6335, 29.7729, 0],
              [-95.633, 29.7736, 0],
              [-95.6321, 29.7739, 0],
              [-95.6252, 29.7736, 0],
              [-95.6248, 29.7735, 0],
              [-95.6235, 29.7728, 0],
              [-95.6232, 29.7727, 0]
            ],
            [
              [-95.6232, 29.7727, 0],
              [-95.6224, 29.7721, 0],
              [-95.6201, 29.7708, 0]
            ],
            [
              [-95.6201, 29.7708, 0],
              [-95.62, 29.7707, 0],
              [-95.619, 29.7702, 0],
              [-95.6185, 29.7697, 0],
              [-95.6183, 29.7695, 0],
              [-95.6183, 29.7687, 0],
              [-95.6188, 29.7659, 0],
              [-95.619, 29.7645, 0],
              [-95.6187, 29.7641, 0],
              [-95.6182, 29.7636, 0],
              [-95.6124, 29.7608, 0],
              [-95.6119, 29.7606, 0],
              [-95.6114, 29.7607, 0],
              [-95.6074, 29.7618, 0],
              [-95.6066, 29.7619, 0],
              [-95.6021, 29.7619, 0],
              [-95.5948, 29.7594, 0],
              [-95.5937, 29.7592, 0],
              [-95.5911, 29.7593, 0],
              [-95.5903, 29.7595, 0],
              [-95.5898, 29.7597, 0],
              [-95.5887, 29.7603, 0],
              [-95.588, 29.761, 0],
              [-95.5871, 29.7626, 0],
              [-95.5864, 29.7641, 0],
              [-95.5861, 29.7647, 0],
              [-95.5857, 29.7652, 0],
              [-95.5852, 29.7655, 0],
              [-95.5841, 29.7658, 0],
              [-95.5831, 29.7659, 0],
              [-95.5811, 29.7659, 0],
              [-95.5802, 29.7661, 0],
              [-95.5796, 29.7665, 0],
              [-95.5793, 29.7668, 0],
              [-95.5786, 29.767, 0],
              [-95.5779, 29.767, 0],
              [-95.5772, 29.7668, 0],
              [-95.5765, 29.7662, 0],
              [-95.5729, 29.7639, 0],
              [-95.5717, 29.763, 0],
              [-95.5707, 29.7625, 0],
              [-95.5693, 29.7622, 0],
              [-95.5683, 29.762, 0],
              [-95.5635, 29.7621, 0],
              [-95.5626, 29.762, 0],
              [-95.5606, 29.7616, 0],
              [-95.5601, 29.7612, 0],
              [-95.5598, 29.7608, 0],
              [-95.5593, 29.7607, 0],
              [-95.5591, 29.7608, 0],
              [-95.5588, 29.7612, 0],
              [-95.5586, 29.7619, 0],
              [-95.5584, 29.762, 0]
            ],
            [
              [-95.6468, 29.7696, 0],
              [-95.6466, 29.7696, 0],
              [-95.6439, 29.7695, 0],
              [-95.6408, 29.7688, 0],
              [-95.6396, 29.769, 0],
              [-95.6361, 29.77, 0],
              [-95.6346, 29.7705, 0],
              [-95.6339, 29.7713, 0],
              [-95.6337, 29.7718, 0],
              [-95.6335, 29.7729, 0],
              [-95.633, 29.7736, 0],
              [-95.6321, 29.7739, 0],
              [-95.6252, 29.7736, 0],
              [-95.6248, 29.7735, 0],
              [-95.6235, 29.7728, 0],
              [-95.6232, 29.7727, 0]
            ],
            [
              [-95.6232, 29.7727, 0],
              [-95.6224, 29.7721, 0],
              [-95.6201, 29.7708, 0]
            ],
            [
              [-95.6201, 29.7708, 0],
              [-95.62, 29.7707, 0],
              [-95.619, 29.7702, 0],
              [-95.6185, 29.7697, 0],
              [-95.6183, 29.7695, 0],
              [-95.6183, 29.7687, 0],
              [-95.6188, 29.7659, 0],
              [-95.619, 29.7645, 0],
              [-95.6187, 29.7641, 0],
              [-95.6182, 29.7636, 0],
              [-95.6124, 29.7608, 0],
              [-95.6119, 29.7606, 0],
              [-95.6114, 29.7607, 0],
              [-95.6074, 29.7618, 0],
              [-95.6066, 29.7619, 0],
              [-95.6021, 29.7619, 0],
              [-95.5948, 29.7594, 0],
              [-95.5937, 29.7592, 0],
              [-95.5911, 29.7593, 0],
              [-95.5903, 29.7595, 0],
              [-95.5898, 29.7597, 0],
              [-95.5887, 29.7603, 0],
              [-95.588, 29.761, 0],
              [-95.5871, 29.7626, 0],
              [-95.5864, 29.7641, 0],
              [-95.5861, 29.7647, 0],
              [-95.5857, 29.7652, 0],
              [-95.5852, 29.7655, 0],
              [-95.5841, 29.7658, 0],
              [-95.5831, 29.7659, 0],
              [-95.5811, 29.7659, 0],
              [-95.5802, 29.7661, 0],
              [-95.5796, 29.7665, 0],
              [-95.5793, 29.7668, 0],
              [-95.5786, 29.767, 0],
              [-95.5779, 29.767, 0],
              [-95.5772, 29.7668, 0],
              [-95.5765, 29.7662, 0],
              [-95.5729, 29.7639, 0],
              [-95.5717, 29.763, 0],
              [-95.5707, 29.7625, 0],
              [-95.5693, 29.7622, 0],
              [-95.5683, 29.762, 0],
              [-95.5635, 29.7621, 0],
              [-95.5626, 29.762, 0],
              [-95.5606, 29.7616, 0],
              [-95.5601, 29.7612, 0],
              [-95.5598, 29.7608, 0],
              [-95.5593, 29.7607, 0],
              [-95.5591, 29.7608, 0],
              [-95.5588, 29.7612, 0],
              [-95.5586, 29.7619, 0],
              [-95.5584, 29.762, 0]
            ],
            [
              [-95.6468, 29.7696, 0],
              [-95.6466, 29.7696, 0],
              [-95.6439, 29.7695, 0],
              [-95.6408, 29.7688, 0],
              [-95.6396, 29.769, 0],
              [-95.6361, 29.77, 0],
              [-95.6346, 29.7705, 0],
              [-95.6339, 29.7713, 0],
              [-95.6337, 29.7718, 0],
              [-95.6335, 29.7729, 0],
              [-95.633, 29.7736, 0],
              [-95.6321, 29.7739, 0],
              [-95.6252, 29.7736, 0],
              [-95.6248, 29.7735, 0],
              [-95.6235, 29.7728, 0],
              [-95.6232, 29.7727, 0]
            ],
            [
              [-95.6232, 29.7727, 0],
              [-95.6224, 29.7721, 0],
              [-95.6201, 29.7708, 0]
            ],
            [
              [-95.6201, 29.7708, 0],
              [-95.62, 29.7707, 0],
              [-95.619, 29.7702, 0],
              [-95.6185, 29.7697, 0],
              [-95.6183, 29.7695, 0],
              [-95.6183, 29.7687, 0],
              [-95.6188, 29.7659, 0],
              [-95.619, 29.7645, 0],
              [-95.6187, 29.7641, 0],
              [-95.6182, 29.7636, 0],
              [-95.6124, 29.7608, 0],
              [-95.6119, 29.7606, 0],
              [-95.6114, 29.7607, 0],
              [-95.6074, 29.7618, 0],
              [-95.6066, 29.7619, 0],
              [-95.6021, 29.7619, 0],
              [-95.5948, 29.7594, 0],
              [-95.5937, 29.7592, 0],
              [-95.5911, 29.7593, 0],
              [-95.5903, 29.7595, 0],
              [-95.5898, 29.7597, 0],
              [-95.5887, 29.7603, 0],
              [-95.588, 29.761, 0],
              [-95.5871, 29.7626, 0],
              [-95.5864, 29.7641, 0],
              [-95.5861, 29.7647, 0],
              [-95.5857, 29.7652, 0],
              [-95.5852, 29.7655, 0],
              [-95.5841, 29.7658, 0],
              [-95.5831, 29.7659, 0],
              [-95.5811, 29.7659, 0],
              [-95.5802, 29.7661, 0],
              [-95.5796, 29.7665, 0],
              [-95.5793, 29.7668, 0],
              [-95.5786, 29.767, 0],
              [-95.5779, 29.767, 0],
              [-95.5772, 29.7668, 0],
              [-95.5765, 29.7662, 0],
              [-95.5729, 29.7639, 0],
              [-95.5717, 29.763, 0],
              [-95.5707, 29.7625, 0],
              [-95.5693, 29.7622, 0],
              [-95.5683, 29.762, 0],
              [-95.5635, 29.7621, 0],
              [-95.5626, 29.762, 0],
              [-95.5606, 29.7616, 0],
              [-95.5601, 29.7612, 0],
              [-95.5598, 29.7608, 0],
              [-95.5593, 29.7607, 0],
              [-95.5591, 29.7608, 0],
              [-95.5588, 29.7612, 0],
              [-95.5586, 29.7619, 0],
              [-95.5584, 29.762, 0]
            ],
            [
              [-95.6468, 29.7696, 0],
              [-95.6466, 29.7696, 0],
              [-95.6439, 29.7695, 0],
              [-95.6408, 29.7688, 0],
              [-95.6396, 29.769, 0],
              [-95.6361, 29.77, 0],
              [-95.6346, 29.7705, 0],
              [-95.6339, 29.7713, 0],
              [-95.6337, 29.7718, 0],
              [-95.6335, 29.7729, 0],
              [-95.633, 29.7736, 0],
              [-95.6321, 29.7739, 0],
              [-95.6252, 29.7736, 0],
              [-95.6248, 29.7735, 0],
              [-95.6235, 29.7728, 0],
              [-95.6232, 29.7727, 0]
            ],
            [
              [-95.6232, 29.7727, 0],
              [-95.6224, 29.7721, 0],
              [-95.6201, 29.7708, 0]
            ],
            [
              [-95.6201, 29.7708, 0],
              [-95.62, 29.7707, 0],
              [-95.619, 29.7702, 0],
              [-95.6185, 29.7697, 0],
              [-95.6183, 29.7695, 0],
              [-95.6183, 29.7687, 0],
              [-95.6188, 29.7659, 0],
              [-95.619, 29.7645, 0],
              [-95.6187, 29.7641, 0],
              [-95.6182, 29.7636, 0],
              [-95.6124, 29.7608, 0],
              [-95.6119, 29.7606, 0],
              [-95.6114, 29.7607, 0],
              [-95.6074, 29.7618, 0],
              [-95.6066, 29.7619, 0],
              [-95.6021, 29.7619, 0],
              [-95.5948, 29.7594, 0],
              [-95.5937, 29.7592, 0],
              [-95.5911, 29.7593, 0],
              [-95.5903, 29.7595, 0],
              [-95.5898, 29.7597, 0],
              [-95.5887, 29.7603, 0],
              [-95.588, 29.761, 0],
              [-95.5871, 29.7626, 0],
              [-95.5864, 29.7641, 0],
              [-95.5861, 29.7647, 0],
              [-95.5857, 29.7652, 0],
              [-95.5852, 29.7655, 0],
              [-95.5841, 29.7658, 0],
              [-95.5831, 29.7659, 0],
              [-95.5811, 29.7659, 0],
              [-95.5802, 29.7661, 0],
              [-95.5796, 29.7665, 0],
              [-95.5793, 29.7668, 0],
              [-95.5786, 29.767, 0],
              [-95.5779, 29.767, 0],
              [-95.5772, 29.7668, 0],
              [-95.5765, 29.7662, 0],
              [-95.5729, 29.7639, 0],
              [-95.5717, 29.763, 0],
              [-95.5707, 29.7625, 0],
              [-95.5693, 29.7622, 0],
              [-95.5683, 29.762, 0],
              [-95.5635, 29.7621, 0],
              [-95.5626, 29.762, 0],
              [-95.5606, 29.7616, 0],
              [-95.5601, 29.7612, 0],
              [-95.5598, 29.7608, 0],
              [-95.5593, 29.7607, 0],
              [-95.5591, 29.7608, 0],
              [-95.5588, 29.7612, 0],
              [-95.5586, 29.7619, 0],
              [-95.5584, 29.762, 0]
            ],
            [
              [-95.6468, 29.7696, 0],
              [-95.6466, 29.7696, 0],
              [-95.6439, 29.7695, 0],
              [-95.6408, 29.7688, 0],
              [-95.6396, 29.769, 0],
              [-95.6361, 29.77, 0],
              [-95.6346, 29.7705, 0],
              [-95.6339, 29.7713, 0],
              [-95.6337, 29.7718, 0],
              [-95.6335, 29.7729, 0],
              [-95.633, 29.7736, 0],
              [-95.6321, 29.7739, 0],
              [-95.6252, 29.7736, 0],
              [-95.6248, 29.7735, 0],
              [-95.6235, 29.7728, 0],
              [-95.6232, 29.7727, 0]
            ],
            [
              [-95.6232, 29.7727, 0],
              [-95.6224, 29.7721, 0],
              [-95.6201, 29.7708, 0]
            ],
            [
              [-95.6201, 29.7708, 0],
              [-95.62, 29.7707, 0],
              [-95.619, 29.7702, 0],
              [-95.6185, 29.7697, 0],
              [-95.6183, 29.7695, 0],
              [-95.6183, 29.7687, 0],
              [-95.6188, 29.7659, 0],
              [-95.619, 29.7645, 0],
              [-95.6187, 29.7641, 0],
              [-95.6182, 29.7636, 0],
              [-95.6124, 29.7608, 0],
              [-95.6119, 29.7606, 0],
              [-95.6114, 29.7607, 0],
              [-95.6074, 29.7618, 0],
              [-95.6066, 29.7619, 0],
              [-95.6021, 29.7619, 0],
              [-95.5948, 29.7594, 0],
              [-95.5937, 29.7592, 0],
              [-95.5911, 29.7593, 0],
              [-95.5903, 29.7595, 0],
              [-95.5898, 29.7597, 0],
              [-95.5887, 29.7603, 0],
              [-95.588, 29.761, 0],
              [-95.5871, 29.7626, 0],
              [-95.5864, 29.7641, 0],
              [-95.5861, 29.7647, 0],
              [-95.5857, 29.7652, 0],
              [-95.5852, 29.7655, 0],
              [-95.5841, 29.7658, 0],
              [-95.5831, 29.7659, 0],
              [-95.5811, 29.7659, 0],
              [-95.5802, 29.7661, 0],
              [-95.5796, 29.7665, 0],
              [-95.5793, 29.7668, 0],
              [-95.5786, 29.767, 0],
              [-95.5779, 29.767, 0],
              [-95.5772, 29.7668, 0],
              [-95.5765, 29.7662, 0],
              [-95.5729, 29.7639, 0],
              [-95.5717, 29.763, 0],
              [-95.5707, 29.7625, 0],
              [-95.5693, 29.7622, 0],
              [-95.5683, 29.762, 0],
              [-95.5635, 29.7621, 0],
              [-95.5626, 29.762, 0],
              [-95.5606, 29.7616, 0],
              [-95.5601, 29.7612, 0],
              [-95.5598, 29.7608, 0],
              [-95.5593, 29.7607, 0],
              [-95.5591, 29.7608, 0],
              [-95.5588, 29.7612, 0],
              [-95.5586, 29.7619, 0],
              [-95.5584, 29.762, 0]
            ],
            [
              [-95.6468, 29.7696, 0],
              [-95.6466, 29.7696, 0],
              [-95.6439, 29.7695, 0],
              [-95.6408, 29.7688, 0],
              [-95.6396, 29.769, 0],
              [-95.6361, 29.77, 0],
              [-95.6346, 29.7705, 0],
              [-95.6339, 29.7713, 0],
              [-95.6337, 29.7718, 0],
              [-95.6335, 29.7729, 0],
              [-95.633, 29.7736, 0],
              [-95.6321, 29.7739, 0],
              [-95.6252, 29.7736, 0],
              [-95.6248, 29.7735, 0],
              [-95.6235, 29.7728, 0],
              [-95.6232, 29.7727, 0]
            ],
            [
              [-95.6232, 29.7727, 0],
              [-95.6224, 29.7721, 0],
              [-95.6201, 29.7708, 0]
            ],
            [
              [-95.6201, 29.7708, 0],
              [-95.62, 29.7707, 0],
              [-95.619, 29.7702, 0],
              [-95.6185, 29.7697, 0],
              [-95.6183, 29.7695, 0],
              [-95.6183, 29.7687, 0],
              [-95.6188, 29.7659, 0],
              [-95.619, 29.7645, 0],
              [-95.6187, 29.7641, 0],
              [-95.6182, 29.7636, 0],
              [-95.6124, 29.7608, 0],
              [-95.6119, 29.7606, 0],
              [-95.6114, 29.7607, 0],
              [-95.6074, 29.7618, 0],
              [-95.6066, 29.7619, 0],
              [-95.6021, 29.7619, 0],
              [-95.5948, 29.7594, 0],
              [-95.5937, 29.7592, 0],
              [-95.5911, 29.7593, 0],
              [-95.5903, 29.7595, 0],
              [-95.5898, 29.7597, 0],
              [-95.5887, 29.7603, 0],
              [-95.588, 29.761, 0],
              [-95.5871, 29.7626, 0],
              [-95.5864, 29.7641, 0],
              [-95.5861, 29.7647, 0],
              [-95.5857, 29.7652, 0],
              [-95.5852, 29.7655, 0],
              [-95.5841, 29.7658, 0],
              [-95.5831, 29.7659, 0],
              [-95.5811, 29.7659, 0],
              [-95.5802, 29.7661, 0],
              [-95.5796, 29.7665, 0],
              [-95.5793, 29.7668, 0],
              [-95.5786, 29.767, 0],
              [-95.5779, 29.767, 0],
              [-95.5772, 29.7668, 0],
              [-95.5765, 29.7662, 0],
              [-95.5729, 29.7639, 0],
              [-95.5717, 29.763, 0],
              [-95.5707, 29.7625, 0],
              [-95.5693, 29.7622, 0],
              [-95.5683, 29.762, 0],
              [-95.5635, 29.7621, 0],
              [-95.5626, 29.762, 0],
              [-95.5606, 29.7616, 0],
              [-95.5601, 29.7612, 0],
              [-95.5598, 29.7608, 0],
              [-95.5593, 29.7607, 0],
              [-95.5591, 29.7608, 0],
              [-95.5588, 29.7612, 0],
              [-95.5586, 29.7619, 0],
              [-95.5584, 29.762, 0]
            ],
            [
              [-95.6468, 29.7696, 0],
              [-95.6466, 29.7696, 0],
              [-95.6439, 29.7695, 0],
              [-95.6408, 29.7688, 0],
              [-95.6396, 29.769, 0],
              [-95.6361, 29.77, 0],
              [-95.6346, 29.7705, 0],
              [-95.6339, 29.7713, 0],
              [-95.6337, 29.7718, 0],
              [-95.6335, 29.7729, 0],
              [-95.633, 29.7736, 0],
              [-95.6321, 29.7739, 0],
              [-95.6252, 29.7736, 0],
              [-95.6248, 29.7735, 0],
              [-95.6235, 29.7728, 0],
              [-95.6232, 29.7727, 0]
            ],
            [
              [-95.6232, 29.7727, 0],
              [-95.6224, 29.7721, 0],
              [-95.6201, 29.7708, 0]
            ],
            [
              [-95.6201, 29.7708, 0],
              [-95.62, 29.7707, 0],
              [-95.619, 29.7702, 0],
              [-95.6185, 29.7697, 0],
              [-95.6183, 29.7695, 0],
              [-95.6183, 29.7687, 0],
              [-95.6188, 29.7659, 0],
              [-95.619, 29.7645, 0],
              [-95.6187, 29.7641, 0],
              [-95.6182, 29.7636, 0],
              [-95.6124, 29.7608, 0],
              [-95.6119, 29.7606, 0],
              [-95.6114, 29.7607, 0],
              [-95.6074, 29.7618, 0],
              [-95.6066, 29.7619, 0],
              [-95.6021, 29.7619, 0],
              [-95.5948, 29.7594, 0],
              [-95.5937, 29.7592, 0],
              [-95.5911, 29.7593, 0],
              [-95.5903, 29.7595, 0],
              [-95.5898, 29.7597, 0],
              [-95.5887, 29.7603, 0],
              [-95.588, 29.761, 0],
              [-95.5871, 29.7626, 0],
              [-95.5864, 29.7641, 0],
              [-95.5861, 29.7647, 0],
              [-95.5857, 29.7652, 0],
              [-95.5852, 29.7655, 0],
              [-95.5841, 29.7658, 0],
              [-95.5831, 29.7659, 0],
              [-95.5811, 29.7659, 0],
              [-95.5802, 29.7661, 0],
              [-95.5796, 29.7665, 0],
              [-95.5793, 29.7668, 0],
              [-95.5786, 29.767, 0],
              [-95.5779, 29.767, 0],
              [-95.5772, 29.7668, 0],
              [-95.5765, 29.7662, 0],
              [-95.5729, 29.7639, 0],
              [-95.5717, 29.763, 0],
              [-95.5707, 29.7625, 0],
              [-95.5693, 29.7622, 0],
              [-95.5683, 29.762, 0],
              [-95.5635, 29.7621, 0],
              [-95.5626, 29.762, 0],
              [-95.5606, 29.7616, 0],
              [-95.5601, 29.7612, 0],
              [-95.5598, 29.7608, 0],
              [-95.5593, 29.7607, 0],
              [-95.5591, 29.7608, 0],
              [-95.5588, 29.7612, 0],
              [-95.5586, 29.7619, 0],
              [-95.5584, 29.762, 0]
            ]
          ]
        ]
      }
    }
  }
}
