{
  "@context": [
    "https://opengeospatial.github.io/ELFIE/json-ld/elf-index.jsonld",
    "https://opengeospatial.github.io/ELFIE/json-ld/hyf.jsonld",
    "http://geojson.org/geojson-ld/geojson-context.jsonld"
  ],
  "@id": "https://opengeospatial.github.io/ELFIE/usgs/nhdplusflowline/uswb/070700051701",
  "@type": "http://www.opengeospatial.org/standards/waterml2/hy_features/HY_HydrographicNetwork",
  "name": "Hydro Network of Indian Creek-Wisconsin River",
  "description": "comment describing the network of each watershed",
  "realizedCatchment": [
    {
      "@id": "https://opengeospatial.github.io/ELFIE/usgs/huc12/uswb/070700051701",
      "@type": "http://www.opengeospatial.org/standards/waterml2/hy_features/HY_Catchment"
    }
  ],
  "networkStation": "https://waterdata.usgs.gov/nwis/inventory/?site_no=05407000",
  "geo": {
    "@type": "schema:GeoCoordinates",
    "schema:latitude": 43.8402,
    "schema:longitude": -89.9538
  },
  "schema:GeoShape": {
    "@type": "FeatureCollection",
    "@id": "https://opengeospatial.github.io/ELFIE/usgs/nhdplusflowline/uswb/070700051701.geojson"
  }
}
