{
  "@context": "https://opengeospatial.github.io/ELFIE/json-ld/elf-index.jsonld",
  "@id": "https://opengeospatial.github.io/ELFIE/tx/roads-major/floodcast/TX_MAJ_127.json",
  "@type": "http://54.225.76.222/geoserver/wfs?service=wfs&version=2.0.0&request=GetFeature&typeNames=ELFIE_MAJOR_TX_RDS&featureID=127",
  "name": "1131123_LOCAL STREETS",
  "description": "This is route ID 1131123 with No Apparent Threat status",
  "geo": {
    "@type": "schema:GeoShape",
    "line": {
      "@context": "http://geojson.org/geojson-ld/geojson-context.jsonld",
      "type": "Feature",
      "id": "https://opengeospatial.github.io/ELFIE/tx/roads-major/floodcast/TX_MAJ_127.json",
      "geometry": {
        "type": "LineString",
        "coordinates": [
          [
            [-95.4738, 29.7614],
            [-95.4734, 29.7615],
            [-95.4731, 29.7616],
            [-95.4727, 29.7617],
            [-95.4724, 29.7617],
            [-95.4721, 29.7618],
            [-95.4711, 29.7618]
          ]
        ]
      }
    }
  }
}
