{
  "@context": "https://opengeospatial.github.io/ELFIE/json-ld/elf-index.jsonld",
  "@id": "https://opengeospatial.github.io/ELFIE/tx/roads-major/floodcast/TX_MAJ_76.json",
  "@type": "http://54.225.76.222/geoserver/wfs?service=wfs&version=2.0.0&request=GetFeature&typeNames=ELFIE_MAJOR_TX_RDS&featureID=76",
  "name": "1124141_LOCAL STREETS",
  "description": "This is route ID 1124141 with Threatened status",
  "geo": {
    "@type": "schema:GeoShape",
    "line": {
      "@context": "http://geojson.org/geojson-ld/geojson-context.jsonld",
      "type": "Feature",
      "id": "https://opengeospatial.github.io/ELFIE/tx/roads-major/floodcast/TX_MAJ_76.json",
      "geometry": {
        "type": "LineString",
        "coordinates": [
          [
            [-95.4677, 29.7655],
            [-95.4673, 29.7654],
            [-95.4671, 29.7655],
            [-95.467, 29.7655],
            [-95.4669, 29.7656],
            [-95.4668, 29.7658],
            [-95.4667, 29.7659],
            [-95.4666, 29.7659],
            [-95.4655, 29.7659],
            [-95.4654, 29.766],
            [-95.4654, 29.7661],
            [-95.4653, 29.7662],
            [-95.4652, 29.7663],
            [-95.465, 29.7664],
            [-95.4636, 29.7666]
          ]
        ]
      }
    }
  }
}
